<?xml version="1.0" ?>
<FlowMonitor>
  <FlowStats>
    <Flow flowId="1" timeFirstTxPacket="+0.0ns" timeFirstRxPacket="+30117.0ns" timeLastTxPacket="+49995870.0ns" timeLastRxPacket="+49984987.0ns" delaySum="+3446455737.0ns" jitterSum="+1926338.0ns" lastDelay="+265347.0ns" txBytes="20349088" rxBytes="20238088" txPackets="13568" rxPackets="13494" lostPackets="0" timesForwarded="26988">
      <delayHistogram nBins="1" >
        <bin index="0" start="0" width="0.001" count="13494" />
      </delayHistogram>
      <jitterHistogram nBins="1" >
        <bin index="0" start="0" width="0.001" count="13493" />
      </jitterHistogram>
      <packetSizeHistogram nBins="76" >
        <bin index="2" start="40" width="20" count="2" />
        <bin index="75" start="1500" width="20" count="13492" />
      </packetSizeHistogram>
      <flowInterruptionsHistogram nBins="0" >
      </flowInterruptionsHistogram>
    </Flow>
    <Flow flowId="2" timeFirstTxPacket="+0.0ns" timeFirstRxPacket="+30156.0ns" timeLastTxPacket="+49999473.0ns" timeLastRxPacket="+49999399.0ns" delaySum="+3566209756.0ns" jitterSum="+2029802.0ns" lastDelay="+266548.0ns" txBytes="21012088" rxBytes="20922088" txPackets="14010" rxPackets="13950" lostPackets="0" timesForwarded="27900">
      <delayHistogram nBins="1" >
        <bin index="0" start="0" width="0.001" count="13950" />
      </delayHistogram>
      <jitterHistogram nBins="1" >
        <bin index="0" start="0" width="0.001" count="13949" />
      </jitterHistogram>
      <packetSizeHistogram nBins="76" >
        <bin index="2" start="40" width="20" count="2" />
        <bin index="75" start="1500" width="20" count="13948" />
      </packetSizeHistogram>
      <flowInterruptionsHistogram nBins="0" >
      </flowInterruptionsHistogram>
    </Flow>
    <Flow flowId="3" timeFirstTxPacket="+0.0ns" timeFirstRxPacket="+30195.0ns" timeLastTxPacket="+49909398.0ns" timeLastRxPacket="+49879299.0ns" delaySum="+3482660169.0ns" jitterSum="+1869813.0ns" lastDelay="+264146.0ns" txBytes="20461588" rxBytes="20328088" txPackets="13643" rxPackets="13554" lostPackets="0" timesForwarded="27108">
      <delayHistogram nBins="1" >
        <bin index="0" start="0" width="0.001" count="13554" />
      </delayHistogram>
      <jitterHistogram nBins="1" >
        <bin index="0" start="0" width="0.001" count="13553" />
      </jitterHistogram>
      <packetSizeHistogram nBins="76" >
        <bin index="2" start="40" width="20" count="2" />
        <bin index="75" start="1500" width="20" count="13552" />
      </packetSizeHistogram>
      <flowInterruptionsHistogram nBins="0" >
      </flowInterruptionsHistogram>
    </Flow>
    <Flow flowId="4" timeFirstTxPacket="+30117.0ns" timeFirstRxPacket="+60234.0ns" timeLastTxPacket="+49984987.0ns" timeLastRxPacket="+49995870.0ns" delaySum="+406035528.0ns" jitterSum="+18.0ns" lastDelay="+30099.0ns" txBytes="539728" rxBytes="539608" txPackets="13493" rxPackets="13490" lostPackets="0" timesForwarded="26980">
      <delayHistogram nBins="1" >
        <bin index="0" start="0" width="0.001" count="13490" />
      </delayHistogram>
      <jitterHistogram nBins="1" >
        <bin index="0" start="0" width="0.001" count="13489" />
      </jitterHistogram>
      <packetSizeHistogram nBins="3" >
        <bin index="2" start="40" width="20" count="13490" />
      </packetSizeHistogram>
      <flowInterruptionsHistogram nBins="0" >
      </flowInterruptionsHistogram>
    </Flow>
    <Flow flowId="5" timeFirstTxPacket="+30156.0ns" timeFirstRxPacket="+60273.0ns" timeLastTxPacket="+49999399.0ns" timeLastRxPacket="+49999473.0ns" delaySum="+419188791.0ns" jitterSum="+18.0ns" lastDelay="+30099.0ns" txBytes="557968" rxBytes="557088" txPackets="13949" rxPackets="13927" lostPackets="0" timesForwarded="27854">
      <delayHistogram nBins="1" >
        <bin index="0" start="0" width="0.001" count="13927" />
      </delayHistogram>
      <jitterHistogram nBins="1" >
        <bin index="0" start="0" width="0.001" count="13926" />
      </jitterHistogram>
      <packetSizeHistogram nBins="3" >
        <bin index="2" start="40" width="20" count="13927" />
      </packetSizeHistogram>
      <flowInterruptionsHistogram nBins="0" >
      </flowInterruptionsHistogram>
    </Flow>
    <Flow flowId="6" timeFirstTxPacket="+30195.0ns" timeFirstRxPacket="+60312.0ns" timeLastTxPacket="+49879299.0ns" timeLastRxPacket="+49909398.0ns" delaySum="+407931765.0ns" jitterSum="+18.0ns" lastDelay="+30099.0ns" txBytes="542128" rxBytes="542128" txPackets="13553" rxPackets="13553" lostPackets="0" timesForwarded="27106">
      <delayHistogram nBins="1" >
        <bin index="0" start="0" width="0.001" count="13553" />
      </delayHistogram>
      <jitterHistogram nBins="1" >
        <bin index="0" start="0" width="0.001" count="13552" />
      </jitterHistogram>
      <packetSizeHistogram nBins="3" >
        <bin index="2" start="40" width="20" count="13553" />
      </packetSizeHistogram>
      <flowInterruptionsHistogram nBins="0" >
      </flowInterruptionsHistogram>
    </Flow>
    <Flow flowId="7" timeFirstTxPacket="+17055214.0ns" timeFirstRxPacket="+17326092.0ns" timeLastTxPacket="+19246663.0ns" timeLastRxPacket="+19445365.0ns" delaySum="+7158386.0ns" jitterSum="+272444.0ns" lastDelay="+198702.0ns" txBytes="33008" rxBytes="33008" txPackets="25" rxPackets="25" lostPackets="0" timesForwarded="50">
      <delayHistogram nBins="1" >
        <bin index="0" start="0" width="0.001" count="25" />
      </delayHistogram>
      <jitterHistogram nBins="1" >
        <bin index="0" start="0" width="0.001" count="24" />
      </jitterHistogram>
      <packetSizeHistogram nBins="76" >
        <bin index="2" start="40" width="20" count="3" />
        <bin index="69" start="1380" width="20" count="1" />
        <bin index="75" start="1500" width="20" count="21" />
      </packetSizeHistogram>
      <flowInterruptionsHistogram nBins="0" >
      </flowInterruptionsHistogram>
    </Flow>
    <Flow flowId="8" timeFirstTxPacket="+17055214.0ns" timeFirstRxPacket="+17326131.0ns" timeLastTxPacket="+19248969.0ns" timeLastRxPacket="+19445398.0ns" delaySum="+7161977.0ns" jitterSum="+277376.0ns" lastDelay="+196429.0ns" txBytes="33008" rxBytes="33008" txPackets="25" rxPackets="25" lostPackets="0" timesForwarded="50">
      <delayHistogram nBins="1" >
        <bin index="0" start="0" width="0.001" count="25" />
      </delayHistogram>
      <jitterHistogram nBins="1" >
        <bin index="0" start="0" width="0.001" count="24" />
      </jitterHistogram>
      <packetSizeHistogram nBins="76" >
        <bin index="2" start="40" width="20" count="3" />
        <bin index="69" start="1380" width="20" count="1" />
        <bin index="75" start="1500" width="20" count="21" />
      </packetSizeHistogram>
      <flowInterruptionsHistogram nBins="0" >
      </flowInterruptionsHistogram>
    </Flow>
    <Flow flowId="9" timeFirstTxPacket="+17055214.0ns" timeFirstRxPacket="+17326170.0ns" timeLastTxPacket="+19252476.0ns" timeLastRxPacket="+19445431.0ns" delaySum="+7170084.0ns" jitterSum="+278421.0ns" lastDelay="+192955.0ns" txBytes="33008" rxBytes="33008" txPackets="25" rxPackets="25" lostPackets="0" timesForwarded="50">
      <delayHistogram nBins="1" >
        <bin index="0" start="0" width="0.001" count="25" />
      </delayHistogram>
      <jitterHistogram nBins="1" >
        <bin index="0" start="0" width="0.001" count="24" />
      </jitterHistogram>
      <packetSizeHistogram nBins="76" >
        <bin index="2" start="40" width="20" count="3" />
        <bin index="69" start="1380" width="20" count="1" />
        <bin index="75" start="1500" width="20" count="21" />
      </packetSizeHistogram>
      <flowInterruptionsHistogram nBins="0" >
      </flowInterruptionsHistogram>
    </Flow>
    <Flow flowId="10" timeFirstTxPacket="+17055214.0ns" timeFirstRxPacket="+17326209.0ns" timeLastTxPacket="+19255983.0ns" timeLastRxPacket="+19445464.0ns" delaySum="+7175885.0ns" jitterSum="+274662.0ns" lastDelay="+189481.0ns" txBytes="33008" rxBytes="33008" txPackets="25" rxPackets="25" lostPackets="0" timesForwarded="50">
      <delayHistogram nBins="1" >
        <bin index="0" start="0" width="0.001" count="25" />
      </delayHistogram>
      <jitterHistogram nBins="1" >
        <bin index="0" start="0" width="0.001" count="24" />
      </jitterHistogram>
      <packetSizeHistogram nBins="76" >
        <bin index="2" start="40" width="20" count="3" />
        <bin index="69" start="1380" width="20" count="1" />
        <bin index="75" start="1500" width="20" count="21" />
      </packetSizeHistogram>
      <flowInterruptionsHistogram nBins="0" >
      </flowInterruptionsHistogram>
    </Flow>
    <Flow flowId="11" timeFirstTxPacket="+17055214.0ns" timeFirstRxPacket="+17326248.0ns" timeLastTxPacket="+19259490.0ns" timeLastRxPacket="+19445497.0ns" delaySum="+7181686.0ns" jitterSum="+273333.0ns" lastDelay="+186007.0ns" txBytes="33008" rxBytes="33008" txPackets="25" rxPackets="25" lostPackets="0" timesForwarded="50">
      <delayHistogram nBins="1" >
        <bin index="0" start="0" width="0.001" count="25" />
      </delayHistogram>
      <jitterHistogram nBins="1" >
        <bin index="0" start="0" width="0.001" count="24" />
      </jitterHistogram>
      <packetSizeHistogram nBins="76" >
        <bin index="2" start="40" width="20" count="3" />
        <bin index="69" start="1380" width="20" count="1" />
        <bin index="75" start="1500" width="20" count="21" />
      </packetSizeHistogram>
      <flowInterruptionsHistogram nBins="0" >
      </flowInterruptionsHistogram>
    </Flow>
    <Flow flowId="12" timeFirstTxPacket="+17055214.0ns" timeFirstRxPacket="+17326287.0ns" timeLastTxPacket="+19262997.0ns" timeLastRxPacket="+19445530.0ns" delaySum="+7187487.0ns" jitterSum="+272054.0ns" lastDelay="+182533.0ns" txBytes="33008" rxBytes="33008" txPackets="25" rxPackets="25" lostPackets="0" timesForwarded="50">
      <delayHistogram nBins="1" >
        <bin index="0" start="0" width="0.001" count="25" />
      </delayHistogram>
      <jitterHistogram nBins="1" >
        <bin index="0" start="0" width="0.001" count="24" />
      </jitterHistogram>
      <packetSizeHistogram nBins="76" >
        <bin index="2" start="40" width="20" count="3" />
        <bin index="69" start="1380" width="20" count="1" />
        <bin index="75" start="1500" width="20" count="21" />
      </packetSizeHistogram>
      <flowInterruptionsHistogram nBins="0" >
      </flowInterruptionsHistogram>
    </Flow>
    <Flow flowId="13" timeFirstTxPacket="+17055214.0ns" timeFirstRxPacket="+17326326.0ns" timeLastTxPacket="+19266504.0ns" timeLastRxPacket="+19445563.0ns" delaySum="+7193288.0ns" jitterSum="+270775.0ns" lastDelay="+179059.0ns" txBytes="33008" rxBytes="33008" txPackets="25" rxPackets="25" lostPackets="0" timesForwarded="50">
      <delayHistogram nBins="1" >
        <bin index="0" start="0" width="0.001" count="25" />
      </delayHistogram>
      <jitterHistogram nBins="1" >
        <bin index="0" start="0" width="0.001" count="24" />
      </jitterHistogram>
      <packetSizeHistogram nBins="76" >
        <bin index="2" start="40" width="20" count="3" />
        <bin index="69" start="1380" width="20" count="1" />
        <bin index="75" start="1500" width="20" count="21" />
      </packetSizeHistogram>
      <flowInterruptionsHistogram nBins="0" >
      </flowInterruptionsHistogram>
    </Flow>
    <Flow flowId="14" timeFirstTxPacket="+17055214.0ns" timeFirstRxPacket="+17326365.0ns" timeLastTxPacket="+19270011.0ns" timeLastRxPacket="+19445596.0ns" delaySum="+7199089.0ns" jitterSum="+269496.0ns" lastDelay="+175585.0ns" txBytes="33008" rxBytes="33008" txPackets="25" rxPackets="25" lostPackets="0" timesForwarded="50">
      <delayHistogram nBins="1" >
        <bin index="0" start="0" width="0.001" count="25" />
      </delayHistogram>
      <jitterHistogram nBins="1" >
        <bin index="0" start="0" width="0.001" count="24" />
      </jitterHistogram>
      <packetSizeHistogram nBins="76" >
        <bin index="2" start="40" width="20" count="3" />
        <bin index="69" start="1380" width="20" count="1" />
        <bin index="75" start="1500" width="20" count="21" />
      </packetSizeHistogram>
      <flowInterruptionsHistogram nBins="0" >
      </flowInterruptionsHistogram>
    </Flow>
    <Flow flowId="15" timeFirstTxPacket="+17055214.0ns" timeFirstRxPacket="+17326404.0ns" timeLastTxPacket="+19273518.0ns" timeLastRxPacket="+19445629.0ns" delaySum="+7204890.0ns" jitterSum="+268217.0ns" lastDelay="+172111.0ns" txBytes="33008" rxBytes="33008" txPackets="25" rxPackets="25" lostPackets="0" timesForwarded="50">
      <delayHistogram nBins="1" >
        <bin index="0" start="0" width="0.001" count="25" />
      </delayHistogram>
      <jitterHistogram nBins="1" >
        <bin index="0" start="0" width="0.001" count="24" />
      </jitterHistogram>
      <packetSizeHistogram nBins="76" >
        <bin index="2" start="40" width="20" count="3" />
        <bin index="69" start="1380" width="20" count="1" />
        <bin index="75" start="1500" width="20" count="21" />
      </packetSizeHistogram>
      <flowInterruptionsHistogram nBins="0" >
      </flowInterruptionsHistogram>
    </Flow>
    <Flow flowId="16" timeFirstTxPacket="+17055214.0ns" timeFirstRxPacket="+17326443.0ns" timeLastTxPacket="+19277025.0ns" timeLastRxPacket="+19445662.0ns" delaySum="+7210691.0ns" jitterSum="+266938.0ns" lastDelay="+168637.0ns" txBytes="33008" rxBytes="33008" txPackets="25" rxPackets="25" lostPackets="0" timesForwarded="50">
      <delayHistogram nBins="1" >
        <bin index="0" start="0" width="0.001" count="25" />
      </delayHistogram>
      <jitterHistogram nBins="1" >
        <bin index="0" start="0" width="0.001" count="24" />
      </jitterHistogram>
      <packetSizeHistogram nBins="76" >
        <bin index="2" start="40" width="20" count="3" />
        <bin index="69" start="1380" width="20" count="1" />
        <bin index="75" start="1500" width="20" count="21" />
      </packetSizeHistogram>
      <flowInterruptionsHistogram nBins="0" >
      </flowInterruptionsHistogram>
    </Flow>
    <Flow flowId="17" timeFirstTxPacket="+17055214.0ns" timeFirstRxPacket="+17326482.0ns" timeLastTxPacket="+19280532.0ns" timeLastRxPacket="+19445695.0ns" delaySum="+7216492.0ns" jitterSum="+265659.0ns" lastDelay="+165163.0ns" txBytes="33008" rxBytes="33008" txPackets="25" rxPackets="25" lostPackets="0" timesForwarded="50">
      <delayHistogram nBins="1" >
        <bin index="0" start="0" width="0.001" count="25" />
      </delayHistogram>
      <jitterHistogram nBins="1" >
        <bin index="0" start="0" width="0.001" count="24" />
      </jitterHistogram>
      <packetSizeHistogram nBins="76" >
        <bin index="2" start="40" width="20" count="3" />
        <bin index="69" start="1380" width="20" count="1" />
        <bin index="75" start="1500" width="20" count="21" />
      </packetSizeHistogram>
      <flowInterruptionsHistogram nBins="0" >
      </flowInterruptionsHistogram>
    </Flow>
    <Flow flowId="18" timeFirstTxPacket="+17055214.0ns" timeFirstRxPacket="+17326521.0ns" timeLastTxPacket="+19284039.0ns" timeLastRxPacket="+19445728.0ns" delaySum="+7222293.0ns" jitterSum="+264380.0ns" lastDelay="+161689.0ns" txBytes="33008" rxBytes="33008" txPackets="25" rxPackets="25" lostPackets="0" timesForwarded="50">
      <delayHistogram nBins="1" >
        <bin index="0" start="0" width="0.001" count="25" />
      </delayHistogram>
      <jitterHistogram nBins="1" >
        <bin index="0" start="0" width="0.001" count="24" />
      </jitterHistogram>
      <packetSizeHistogram nBins="76" >
        <bin index="2" start="40" width="20" count="3" />
        <bin index="69" start="1380" width="20" count="1" />
        <bin index="75" start="1500" width="20" count="21" />
      </packetSizeHistogram>
      <flowInterruptionsHistogram nBins="0" >
      </flowInterruptionsHistogram>
    </Flow>
    <Flow flowId="19" timeFirstTxPacket="+17055214.0ns" timeFirstRxPacket="+17326560.0ns" timeLastTxPacket="+19287546.0ns" timeLastRxPacket="+19445761.0ns" delaySum="+7228094.0ns" jitterSum="+263101.0ns" lastDelay="+158215.0ns" txBytes="33008" rxBytes="33008" txPackets="25" rxPackets="25" lostPackets="0" timesForwarded="50">
      <delayHistogram nBins="1" >
        <bin index="0" start="0" width="0.001" count="25" />
      </delayHistogram>
      <jitterHistogram nBins="1" >
        <bin index="0" start="0" width="0.001" count="24" />
      </jitterHistogram>
      <packetSizeHistogram nBins="76" >
        <bin index="2" start="40" width="20" count="3" />
        <bin index="69" start="1380" width="20" count="1" />
        <bin index="75" start="1500" width="20" count="21" />
      </packetSizeHistogram>
      <flowInterruptionsHistogram nBins="0" >
      </flowInterruptionsHistogram>
    </Flow>
    <Flow flowId="20" timeFirstTxPacket="+17055214.0ns" timeFirstRxPacket="+17326599.0ns" timeLastTxPacket="+19291053.0ns" timeLastRxPacket="+19445794.0ns" delaySum="+7233895.0ns" jitterSum="+261822.0ns" lastDelay="+154741.0ns" txBytes="33008" rxBytes="33008" txPackets="25" rxPackets="25" lostPackets="0" timesForwarded="50">
      <delayHistogram nBins="1" >
        <bin index="0" start="0" width="0.001" count="25" />
      </delayHistogram>
      <jitterHistogram nBins="1" >
        <bin index="0" start="0" width="0.001" count="24" />
      </jitterHistogram>
      <packetSizeHistogram nBins="76" >
        <bin index="2" start="40" width="20" count="3" />
        <bin index="69" start="1380" width="20" count="1" />
        <bin index="75" start="1500" width="20" count="21" />
      </packetSizeHistogram>
      <flowInterruptionsHistogram nBins="0" >
      </flowInterruptionsHistogram>
    </Flow>
    <Flow flowId="21" timeFirstTxPacket="+17055214.0ns" timeFirstRxPacket="+17326638.0ns" timeLastTxPacket="+19294560.0ns" timeLastRxPacket="+19445827.0ns" delaySum="+7239696.0ns" jitterSum="+260543.0ns" lastDelay="+151267.0ns" txBytes="33008" rxBytes="33008" txPackets="25" rxPackets="25" lostPackets="0" timesForwarded="50">
      <delayHistogram nBins="1" >
        <bin index="0" start="0" width="0.001" count="25" />
      </delayHistogram>
      <jitterHistogram nBins="1" >
        <bin index="0" start="0" width="0.001" count="24" />
      </jitterHistogram>
      <packetSizeHistogram nBins="76" >
        <bin index="2" start="40" width="20" count="3" />
        <bin index="69" start="1380" width="20" count="1" />
        <bin index="75" start="1500" width="20" count="21" />
      </packetSizeHistogram>
      <flowInterruptionsHistogram nBins="0" >
      </flowInterruptionsHistogram>
    </Flow>
    <Flow flowId="22" timeFirstTxPacket="+17055214.0ns" timeFirstRxPacket="+17326677.0ns" timeLastTxPacket="+19298067.0ns" timeLastRxPacket="+19445860.0ns" delaySum="+7245497.0ns" jitterSum="+259264.0ns" lastDelay="+147793.0ns" txBytes="33008" rxBytes="33008" txPackets="25" rxPackets="25" lostPackets="0" timesForwarded="50">
      <delayHistogram nBins="1" >
        <bin index="0" start="0" width="0.001" count="25" />
      </delayHistogram>
      <jitterHistogram nBins="1" >
        <bin index="0" start="0" width="0.001" count="24" />
      </jitterHistogram>
      <packetSizeHistogram nBins="76" >
        <bin index="2" start="40" width="20" count="3" />
        <bin index="69" start="1380" width="20" count="1" />
        <bin index="75" start="1500" width="20" count="21" />
      </packetSizeHistogram>
      <flowInterruptionsHistogram nBins="0" >
      </flowInterruptionsHistogram>
    </Flow>
    <Flow flowId="23" timeFirstTxPacket="+17055214.0ns" timeFirstRxPacket="+17326716.0ns" timeLastTxPacket="+19301574.0ns" timeLastRxPacket="+19445893.0ns" delaySum="+7251298.0ns" jitterSum="+257985.0ns" lastDelay="+144319.0ns" txBytes="33008" rxBytes="33008" txPackets="25" rxPackets="25" lostPackets="0" timesForwarded="50">
      <delayHistogram nBins="1" >
        <bin index="0" start="0" width="0.001" count="25" />
      </delayHistogram>
      <jitterHistogram nBins="1" >
        <bin index="0" start="0" width="0.001" count="24" />
      </jitterHistogram>
      <packetSizeHistogram nBins="76" >
        <bin index="2" start="40" width="20" count="3" />
        <bin index="69" start="1380" width="20" count="1" />
        <bin index="75" start="1500" width="20" count="21" />
      </packetSizeHistogram>
      <flowInterruptionsHistogram nBins="0" >
      </flowInterruptionsHistogram>
    </Flow>
    <Flow flowId="24" timeFirstTxPacket="+17055214.0ns" timeFirstRxPacket="+17326755.0ns" timeLastTxPacket="+19305081.0ns" timeLastRxPacket="+19445926.0ns" delaySum="+7257099.0ns" jitterSum="+256706.0ns" lastDelay="+140845.0ns" txBytes="33008" rxBytes="33008" txPackets="25" rxPackets="25" lostPackets="0" timesForwarded="50">
      <delayHistogram nBins="1" >
        <bin index="0" start="0" width="0.001" count="25" />
      </delayHistogram>
      <jitterHistogram nBins="1" >
        <bin index="0" start="0" width="0.001" count="24" />
      </jitterHistogram>
      <packetSizeHistogram nBins="76" >
        <bin index="2" start="40" width="20" count="3" />
        <bin index="69" start="1380" width="20" count="1" />
        <bin index="75" start="1500" width="20" count="21" />
      </packetSizeHistogram>
      <flowInterruptionsHistogram nBins="0" >
      </flowInterruptionsHistogram>
    </Flow>
    <Flow flowId="25" timeFirstTxPacket="+17055214.0ns" timeFirstRxPacket="+17326794.0ns" timeLastTxPacket="+19308588.0ns" timeLastRxPacket="+19445959.0ns" delaySum="+7262900.0ns" jitterSum="+260231.0ns" lastDelay="+137371.0ns" txBytes="33008" rxBytes="33008" txPackets="25" rxPackets="25" lostPackets="0" timesForwarded="50">
      <delayHistogram nBins="1" >
        <bin index="0" start="0" width="0.001" count="25" />
      </delayHistogram>
      <jitterHistogram nBins="1" >
        <bin index="0" start="0" width="0.001" count="24" />
      </jitterHistogram>
      <packetSizeHistogram nBins="76" >
        <bin index="2" start="40" width="20" count="3" />
        <bin index="69" start="1380" width="20" count="1" />
        <bin index="75" start="1500" width="20" count="21" />
      </packetSizeHistogram>
      <flowInterruptionsHistogram nBins="0" >
      </flowInterruptionsHistogram>
    </Flow>
    <Flow flowId="26" timeFirstTxPacket="+17055214.0ns" timeFirstRxPacket="+17326833.0ns" timeLastTxPacket="+19310894.0ns" timeLastRxPacket="+19445992.0ns" delaySum="+7267500.0ns" jitterSum="+262555.0ns" lastDelay="+135098.0ns" txBytes="33008" rxBytes="33008" txPackets="25" rxPackets="25" lostPackets="0" timesForwarded="50">
      <delayHistogram nBins="1" >
        <bin index="0" start="0" width="0.001" count="25" />
      </delayHistogram>
      <jitterHistogram nBins="1" >
        <bin index="0" start="0" width="0.001" count="24" />
      </jitterHistogram>
      <packetSizeHistogram nBins="76" >
        <bin index="2" start="40" width="20" count="3" />
        <bin index="69" start="1380" width="20" count="1" />
        <bin index="75" start="1500" width="20" count="21" />
      </packetSizeHistogram>
      <flowInterruptionsHistogram nBins="0" >
      </flowInterruptionsHistogram>
    </Flow>
    <Flow flowId="27" timeFirstTxPacket="+17326092.0ns" timeFirstRxPacket="+17356209.0ns" timeLastTxPacket="+19216531.0ns" timeLastRxPacket="+19246663.0ns" delaySum="+722427.0ns" jitterSum="+51.0ns" lastDelay="+30132.0ns" txBytes="968" rxBytes="968" txPackets="24" rxPackets="24" lostPackets="0" timesForwarded="48">
      <delayHistogram nBins="1" >
        <bin index="0" start="0" width="0.001" count="24" />
      </delayHistogram>
      <jitterHistogram nBins="1" >
        <bin index="0" start="0" width="0.001" count="23" />
      </jitterHistogram>
      <packetSizeHistogram nBins="3" >
        <bin index="2" start="40" width="20" count="24" />
      </packetSizeHistogram>
      <flowInterruptionsHistogram nBins="0" >
      </flowInterruptionsHistogram>
    </Flow>
    <Flow flowId="28" timeFirstTxPacket="+17326131.0ns" timeFirstRxPacket="+17356248.0ns" timeLastTxPacket="+19218837.0ns" timeLastRxPacket="+19248969.0ns" delaySum="+722427.0ns" jitterSum="+51.0ns" lastDelay="+30132.0ns" txBytes="968" rxBytes="968" txPackets="24" rxPackets="24" lostPackets="0" timesForwarded="48">
      <delayHistogram nBins="1" >
        <bin index="0" start="0" width="0.001" count="24" />
      </delayHistogram>
      <jitterHistogram nBins="1" >
        <bin index="0" start="0" width="0.001" count="23" />
      </jitterHistogram>
      <packetSizeHistogram nBins="3" >
        <bin index="2" start="40" width="20" count="24" />
      </packetSizeHistogram>
      <flowInterruptionsHistogram nBins="0" >
      </flowInterruptionsHistogram>
    </Flow>
    <Flow flowId="29" timeFirstTxPacket="+17326170.0ns" timeFirstRxPacket="+17356287.0ns" timeLastTxPacket="+19222344.0ns" timeLastRxPacket="+19252476.0ns" delaySum="+722427.0ns" jitterSum="+51.0ns" lastDelay="+30132.0ns" txBytes="968" rxBytes="968" txPackets="24" rxPackets="24" lostPackets="0" timesForwarded="48">
      <delayHistogram nBins="1" >
        <bin index="0" start="0" width="0.001" count="24" />
      </delayHistogram>
      <jitterHistogram nBins="1" >
        <bin index="0" start="0" width="0.001" count="23" />
      </jitterHistogram>
      <packetSizeHistogram nBins="3" >
        <bin index="2" start="40" width="20" count="24" />
      </packetSizeHistogram>
      <flowInterruptionsHistogram nBins="0" >
      </flowInterruptionsHistogram>
    </Flow>
    <Flow flowId="30" timeFirstTxPacket="+17326209.0ns" timeFirstRxPacket="+17356326.0ns" timeLastTxPacket="+19225851.0ns" timeLastRxPacket="+19255983.0ns" delaySum="+722427.0ns" jitterSum="+51.0ns" lastDelay="+30132.0ns" txBytes="968" rxBytes="968" txPackets="24" rxPackets="24" lostPackets="0" timesForwarded="48">
      <delayHistogram nBins="1" >
        <bin index="0" start="0" width="0.001" count="24" />
      </delayHistogram>
      <jitterHistogram nBins="1" >
        <bin index="0" start="0" width="0.001" count="23" />
      </jitterHistogram>
      <packetSizeHistogram nBins="3" >
        <bin index="2" start="40" width="20" count="24" />
      </packetSizeHistogram>
      <flowInterruptionsHistogram nBins="0" >
      </flowInterruptionsHistogram>
    </Flow>
    <Flow flowId="31" timeFirstTxPacket="+17326248.0ns" timeFirstRxPacket="+17356365.0ns" timeLastTxPacket="+19229358.0ns" timeLastRxPacket="+19259490.0ns" delaySum="+722427.0ns" jitterSum="+51.0ns" lastDelay="+30132.0ns" txBytes="968" rxBytes="968" txPackets="24" rxPackets="24" lostPackets="0" timesForwarded="48">
      <delayHistogram nBins="1" >
        <bin index="0" start="0" width="0.001" count="24" />
      </delayHistogram>
      <jitterHistogram nBins="1" >
        <bin index="0" start="0" width="0.001" count="23" />
      </jitterHistogram>
      <packetSizeHistogram nBins="3" >
        <bin index="2" start="40" width="20" count="24" />
      </packetSizeHistogram>
      <flowInterruptionsHistogram nBins="0" >
      </flowInterruptionsHistogram>
    </Flow>
    <Flow flowId="32" timeFirstTxPacket="+17326287.0ns" timeFirstRxPacket="+17356404.0ns" timeLastTxPacket="+19232865.0ns" timeLastRxPacket="+19262997.0ns" delaySum="+722427.0ns" jitterSum="+51.0ns" lastDelay="+30132.0ns" txBytes="968" rxBytes="968" txPackets="24" rxPackets="24" lostPackets="0" timesForwarded="48">
      <delayHistogram nBins="1" >
        <bin index="0" start="0" width="0.001" count="24" />
      </delayHistogram>
      <jitterHistogram nBins="1" >
        <bin index="0" start="0" width="0.001" count="23" />
      </jitterHistogram>
      <packetSizeHistogram nBins="3" >
        <bin index="2" start="40" width="20" count="24" />
      </packetSizeHistogram>
      <flowInterruptionsHistogram nBins="0" >
      </flowInterruptionsHistogram>
    </Flow>
    <Flow flowId="33" timeFirstTxPacket="+17326326.0ns" timeFirstRxPacket="+17356443.0ns" timeLastTxPacket="+19236372.0ns" timeLastRxPacket="+19266504.0ns" delaySum="+722427.0ns" jitterSum="+51.0ns" lastDelay="+30132.0ns" txBytes="968" rxBytes="968" txPackets="24" rxPackets="24" lostPackets="0" timesForwarded="48">
      <delayHistogram nBins="1" >
        <bin index="0" start="0" width="0.001" count="24" />
      </delayHistogram>
      <jitterHistogram nBins="1" >
        <bin index="0" start="0" width="0.001" count="23" />
      </jitterHistogram>
      <packetSizeHistogram nBins="3" >
        <bin index="2" start="40" width="20" count="24" />
      </packetSizeHistogram>
      <flowInterruptionsHistogram nBins="0" >
      </flowInterruptionsHistogram>
    </Flow>
    <Flow flowId="34" timeFirstTxPacket="+17326365.0ns" timeFirstRxPacket="+17356482.0ns" timeLastTxPacket="+19239879.0ns" timeLastRxPacket="+19270011.0ns" delaySum="+722427.0ns" jitterSum="+51.0ns" lastDelay="+30132.0ns" txBytes="968" rxBytes="968" txPackets="24" rxPackets="24" lostPackets="0" timesForwarded="48">
      <delayHistogram nBins="1" >
        <bin index="0" start="0" width="0.001" count="24" />
      </delayHistogram>
      <jitterHistogram nBins="1" >
        <bin index="0" start="0" width="0.001" count="23" />
      </jitterHistogram>
      <packetSizeHistogram nBins="3" >
        <bin index="2" start="40" width="20" count="24" />
      </packetSizeHistogram>
      <flowInterruptionsHistogram nBins="0" >
      </flowInterruptionsHistogram>
    </Flow>
    <Flow flowId="35" timeFirstTxPacket="+17326404.0ns" timeFirstRxPacket="+17356521.0ns" timeLastTxPacket="+19243386.0ns" timeLastRxPacket="+19273518.0ns" delaySum="+722427.0ns" jitterSum="+51.0ns" lastDelay="+30132.0ns" txBytes="968" rxBytes="968" txPackets="24" rxPackets="24" lostPackets="0" timesForwarded="48">
      <delayHistogram nBins="1" >
        <bin index="0" start="0" width="0.001" count="24" />
      </delayHistogram>
      <jitterHistogram nBins="1" >
        <bin index="0" start="0" width="0.001" count="23" />
      </jitterHistogram>
      <packetSizeHistogram nBins="3" >
        <bin index="2" start="40" width="20" count="24" />
      </packetSizeHistogram>
      <flowInterruptionsHistogram nBins="0" >
      </flowInterruptionsHistogram>
    </Flow>
    <Flow flowId="36" timeFirstTxPacket="+17326443.0ns" timeFirstRxPacket="+17356560.0ns" timeLastTxPacket="+19246893.0ns" timeLastRxPacket="+19277025.0ns" delaySum="+722427.0ns" jitterSum="+51.0ns" lastDelay="+30132.0ns" txBytes="968" rxBytes="968" txPackets="24" rxPackets="24" lostPackets="0" timesForwarded="48">
      <delayHistogram nBins="1" >
        <bin index="0" start="0" width="0.001" count="24" />
      </delayHistogram>
      <jitterHistogram nBins="1" >
        <bin index="0" start="0" width="0.001" count="23" />
      </jitterHistogram>
      <packetSizeHistogram nBins="3" >
        <bin index="2" start="40" width="20" count="24" />
      </packetSizeHistogram>
      <flowInterruptionsHistogram nBins="0" >
      </flowInterruptionsHistogram>
    </Flow>
    <Flow flowId="37" timeFirstTxPacket="+17326482.0ns" timeFirstRxPacket="+17356599.0ns" timeLastTxPacket="+19250400.0ns" timeLastRxPacket="+19280532.0ns" delaySum="+722427.0ns" jitterSum="+51.0ns" lastDelay="+30132.0ns" txBytes="968" rxBytes="968" txPackets="24" rxPackets="24" lostPackets="0" timesForwarded="48">
      <delayHistogram nBins="1" >
        <bin index="0" start="0" width="0.001" count="24" />
      </delayHistogram>
      <jitterHistogram nBins="1" >
        <bin index="0" start="0" width="0.001" count="23" />
      </jitterHistogram>
      <packetSizeHistogram nBins="3" >
        <bin index="2" start="40" width="20" count="24" />
      </packetSizeHistogram>
      <flowInterruptionsHistogram nBins="0" >
      </flowInterruptionsHistogram>
    </Flow>
    <Flow flowId="38" timeFirstTxPacket="+17326521.0ns" timeFirstRxPacket="+17356638.0ns" timeLastTxPacket="+19253907.0ns" timeLastRxPacket="+19284039.0ns" delaySum="+722427.0ns" jitterSum="+51.0ns" lastDelay="+30132.0ns" txBytes="968" rxBytes="968" txPackets="24" rxPackets="24" lostPackets="0" timesForwarded="48">
      <delayHistogram nBins="1" >
        <bin index="0" start="0" width="0.001" count="24" />
      </delayHistogram>
      <jitterHistogram nBins="1" >
        <bin index="0" start="0" width="0.001" count="23" />
      </jitterHistogram>
      <packetSizeHistogram nBins="3" >
        <bin index="2" start="40" width="20" count="24" />
      </packetSizeHistogram>
      <flowInterruptionsHistogram nBins="0" >
      </flowInterruptionsHistogram>
    </Flow>
    <Flow flowId="39" timeFirstTxPacket="+17326560.0ns" timeFirstRxPacket="+17356677.0ns" timeLastTxPacket="+19257414.0ns" timeLastRxPacket="+19287546.0ns" delaySum="+722427.0ns" jitterSum="+51.0ns" lastDelay="+30132.0ns" txBytes="968" rxBytes="968" txPackets="24" rxPackets="24" lostPackets="0" timesForwarded="48">
      <delayHistogram nBins="1" >
        <bin index="0" start="0" width="0.001" count="24" />
      </delayHistogram>
      <jitterHistogram nBins="1" >
        <bin index="0" start="0" width="0.001" count="23" />
      </jitterHistogram>
      <packetSizeHistogram nBins="3" >
        <bin index="2" start="40" width="20" count="24" />
      </packetSizeHistogram>
      <flowInterruptionsHistogram nBins="0" >
      </flowInterruptionsHistogram>
    </Flow>
    <Flow flowId="40" timeFirstTxPacket="+17326599.0ns" timeFirstRxPacket="+17356716.0ns" timeLastTxPacket="+19260921.0ns" timeLastRxPacket="+19291053.0ns" delaySum="+722427.0ns" jitterSum="+51.0ns" lastDelay="+30132.0ns" txBytes="968" rxBytes="968" txPackets="24" rxPackets="24" lostPackets="0" timesForwarded="48">
      <delayHistogram nBins="1" >
        <bin index="0" start="0" width="0.001" count="24" />
      </delayHistogram>
      <jitterHistogram nBins="1" >
        <bin index="0" start="0" width="0.001" count="23" />
      </jitterHistogram>
      <packetSizeHistogram nBins="3" >
        <bin index="2" start="40" width="20" count="24" />
      </packetSizeHistogram>
      <flowInterruptionsHistogram nBins="0" >
      </flowInterruptionsHistogram>
    </Flow>
    <Flow flowId="41" timeFirstTxPacket="+17326638.0ns" timeFirstRxPacket="+17356755.0ns" timeLastTxPacket="+19264428.0ns" timeLastRxPacket="+19294560.0ns" delaySum="+722427.0ns" jitterSum="+51.0ns" lastDelay="+30132.0ns" txBytes="968" rxBytes="968" txPackets="24" rxPackets="24" lostPackets="0" timesForwarded="48">
      <delayHistogram nBins="1" >
        <bin index="0" start="0" width="0.001" count="24" />
      </delayHistogram>
      <jitterHistogram nBins="1" >
        <bin index="0" start="0" width="0.001" count="23" />
      </jitterHistogram>
      <packetSizeHistogram nBins="3" >
        <bin index="2" start="40" width="20" count="24" />
      </packetSizeHistogram>
      <flowInterruptionsHistogram nBins="0" >
      </flowInterruptionsHistogram>
    </Flow>
    <Flow flowId="42" timeFirstTxPacket="+17326677.0ns" timeFirstRxPacket="+17356794.0ns" timeLastTxPacket="+19267935.0ns" timeLastRxPacket="+19298067.0ns" delaySum="+722427.0ns" jitterSum="+51.0ns" lastDelay="+30132.0ns" txBytes="968" rxBytes="968" txPackets="24" rxPackets="24" lostPackets="0" timesForwarded="48">
      <delayHistogram nBins="1" >
        <bin index="0" start="0" width="0.001" count="24" />
      </delayHistogram>
      <jitterHistogram nBins="1" >
        <bin index="0" start="0" width="0.001" count="23" />
      </jitterHistogram>
      <packetSizeHistogram nBins="3" >
        <bin index="2" start="40" width="20" count="24" />
      </packetSizeHistogram>
      <flowInterruptionsHistogram nBins="0" >
      </flowInterruptionsHistogram>
    </Flow>
    <Flow flowId="43" timeFirstTxPacket="+17326716.0ns" timeFirstRxPacket="+17356833.0ns" timeLastTxPacket="+19271442.0ns" timeLastRxPacket="+19301574.0ns" delaySum="+722427.0ns" jitterSum="+51.0ns" lastDelay="+30132.0ns" txBytes="968" rxBytes="968" txPackets="24" rxPackets="24" lostPackets="0" timesForwarded="48">
      <delayHistogram nBins="1" >
        <bin index="0" start="0" width="0.001" count="24" />
      </delayHistogram>
      <jitterHistogram nBins="1" >
        <bin index="0" start="0" width="0.001" count="23" />
      </jitterHistogram>
      <packetSizeHistogram nBins="3" >
        <bin index="2" start="40" width="20" count="24" />
      </packetSizeHistogram>
      <flowInterruptionsHistogram nBins="0" >
      </flowInterruptionsHistogram>
    </Flow>
    <Flow flowId="44" timeFirstTxPacket="+17326755.0ns" timeFirstRxPacket="+17356872.0ns" timeLastTxPacket="+19274949.0ns" timeLastRxPacket="+19305081.0ns" delaySum="+722427.0ns" jitterSum="+51.0ns" lastDelay="+30132.0ns" txBytes="968" rxBytes="968" txPackets="24" rxPackets="24" lostPackets="0" timesForwarded="48">
      <delayHistogram nBins="1" >
        <bin index="0" start="0" width="0.001" count="24" />
      </delayHistogram>
      <jitterHistogram nBins="1" >
        <bin index="0" start="0" width="0.001" count="23" />
      </jitterHistogram>
      <packetSizeHistogram nBins="3" >
        <bin index="2" start="40" width="20" count="24" />
      </packetSizeHistogram>
      <flowInterruptionsHistogram nBins="0" >
      </flowInterruptionsHistogram>
    </Flow>
    <Flow flowId="45" timeFirstTxPacket="+17326794.0ns" timeFirstRxPacket="+17356911.0ns" timeLastTxPacket="+19278456.0ns" timeLastRxPacket="+19308588.0ns" delaySum="+722427.0ns" jitterSum="+51.0ns" lastDelay="+30132.0ns" txBytes="968" rxBytes="968" txPackets="24" rxPackets="24" lostPackets="0" timesForwarded="48">
      <delayHistogram nBins="1" >
        <bin index="0" start="0" width="0.001" count="24" />
      </delayHistogram>
      <jitterHistogram nBins="1" >
        <bin index="0" start="0" width="0.001" count="23" />
      </jitterHistogram>
      <packetSizeHistogram nBins="3" >
        <bin index="2" start="40" width="20" count="24" />
      </packetSizeHistogram>
      <flowInterruptionsHistogram nBins="0" >
      </flowInterruptionsHistogram>
    </Flow>
    <Flow flowId="46" timeFirstTxPacket="+17326833.0ns" timeFirstRxPacket="+17356950.0ns" timeLastTxPacket="+19280762.0ns" timeLastRxPacket="+19310894.0ns" delaySum="+722427.0ns" jitterSum="+51.0ns" lastDelay="+30132.0ns" txBytes="968" rxBytes="968" txPackets="24" rxPackets="24" lostPackets="0" timesForwarded="48">
      <delayHistogram nBins="1" >
        <bin index="0" start="0" width="0.001" count="24" />
      </delayHistogram>
      <jitterHistogram nBins="1" >
        <bin index="0" start="0" width="0.001" count="23" />
      </jitterHistogram>
      <packetSizeHistogram nBins="3" >
        <bin index="2" start="40" width="20" count="24" />
      </packetSizeHistogram>
      <flowInterruptionsHistogram nBins="0" >
      </flowInterruptionsHistogram>
    </Flow>
  </FlowStats>
  <Ipv4FlowClassifier>
    <Flow flowId="1" sourceAddress="10.0.1.1" destinationAddress="10.0.25.2" protocol="6" sourcePort="49153" destinationPort="50000">
      <Dscp value="0x0" packets="13568" />
    </Flow>
    <Flow flowId="2" sourceAddress="10.0.2.1" destinationAddress="10.0.25.2" protocol="6" sourcePort="49153" destinationPort="50000">
      <Dscp value="0x0" packets="14010" />
    </Flow>
    <Flow flowId="3" sourceAddress="10.0.3.1" destinationAddress="10.0.25.2" protocol="6" sourcePort="49153" destinationPort="50000">
      <Dscp value="0x0" packets="13643" />
    </Flow>
    <Flow flowId="7" sourceAddress="10.0.4.1" destinationAddress="10.0.26.2" protocol="6" sourcePort="49153" destinationPort="50000">
      <Dscp value="0x0" packets="25" />
    </Flow>
    <Flow flowId="8" sourceAddress="10.0.5.1" destinationAddress="10.0.26.2" protocol="6" sourcePort="49153" destinationPort="50000">
      <Dscp value="0x0" packets="25" />
    </Flow>
    <Flow flowId="9" sourceAddress="10.0.6.1" destinationAddress="10.0.26.2" protocol="6" sourcePort="49153" destinationPort="50000">
      <Dscp value="0x0" packets="25" />
    </Flow>
    <Flow flowId="10" sourceAddress="10.0.7.1" destinationAddress="10.0.26.2" protocol="6" sourcePort="49153" destinationPort="50000">
      <Dscp value="0x0" packets="25" />
    </Flow>
    <Flow flowId="11" sourceAddress="10.0.8.1" destinationAddress="10.0.26.2" protocol="6" sourcePort="49153" destinationPort="50000">
      <Dscp value="0x0" packets="25" />
    </Flow>
    <Flow flowId="12" sourceAddress="10.0.9.1" destinationAddress="10.0.26.2" protocol="6" sourcePort="49153" destinationPort="50000">
      <Dscp value="0x0" packets="25" />
    </Flow>
    <Flow flowId="13" sourceAddress="10.0.10.1" destinationAddress="10.0.26.2" protocol="6" sourcePort="49153" destinationPort="50000">
      <Dscp value="0x0" packets="25" />
    </Flow>
    <Flow flowId="14" sourceAddress="10.0.11.1" destinationAddress="10.0.26.2" protocol="6" sourcePort="49153" destinationPort="50000">
      <Dscp value="0x0" packets="25" />
    </Flow>
    <Flow flowId="15" sourceAddress="10.0.12.1" destinationAddress="10.0.26.2" protocol="6" sourcePort="49153" destinationPort="50000">
      <Dscp value="0x0" packets="25" />
    </Flow>
    <Flow flowId="16" sourceAddress="10.0.13.1" destinationAddress="10.0.26.2" protocol="6" sourcePort="49153" destinationPort="50000">
      <Dscp value="0x0" packets="25" />
    </Flow>
    <Flow flowId="17" sourceAddress="10.0.14.1" destinationAddress="10.0.26.2" protocol="6" sourcePort="49153" destinationPort="50000">
      <Dscp value="0x0" packets="25" />
    </Flow>
    <Flow flowId="18" sourceAddress="10.0.15.1" destinationAddress="10.0.26.2" protocol="6" sourcePort="49153" destinationPort="50000">
      <Dscp value="0x0" packets="25" />
    </Flow>
    <Flow flowId="19" sourceAddress="10.0.16.1" destinationAddress="10.0.26.2" protocol="6" sourcePort="49153" destinationPort="50000">
      <Dscp value="0x0" packets="25" />
    </Flow>
    <Flow flowId="20" sourceAddress="10.0.17.1" destinationAddress="10.0.26.2" protocol="6" sourcePort="49153" destinationPort="50000">
      <Dscp value="0x0" packets="25" />
    </Flow>
    <Flow flowId="21" sourceAddress="10.0.18.1" destinationAddress="10.0.26.2" protocol="6" sourcePort="49153" destinationPort="50000">
      <Dscp value="0x0" packets="25" />
    </Flow>
    <Flow flowId="22" sourceAddress="10.0.19.1" destinationAddress="10.0.26.2" protocol="6" sourcePort="49153" destinationPort="50000">
      <Dscp value="0x0" packets="25" />
    </Flow>
    <Flow flowId="23" sourceAddress="10.0.20.1" destinationAddress="10.0.26.2" protocol="6" sourcePort="49153" destinationPort="50000">
      <Dscp value="0x0" packets="25" />
    </Flow>
    <Flow flowId="24" sourceAddress="10.0.21.1" destinationAddress="10.0.26.2" protocol="6" sourcePort="49153" destinationPort="50000">
      <Dscp value="0x0" packets="25" />
    </Flow>
    <Flow flowId="25" sourceAddress="10.0.22.1" destinationAddress="10.0.26.2" protocol="6" sourcePort="49153" destinationPort="50000">
      <Dscp value="0x0" packets="25" />
    </Flow>
    <Flow flowId="26" sourceAddress="10.0.23.1" destinationAddress="10.0.26.2" protocol="6" sourcePort="49153" destinationPort="50000">
      <Dscp value="0x0" packets="25" />
    </Flow>
    <Flow flowId="4" sourceAddress="10.0.25.2" destinationAddress="10.0.1.1" protocol="6" sourcePort="50000" destinationPort="49153">
      <Dscp value="0x0" packets="13493" />
    </Flow>
    <Flow flowId="5" sourceAddress="10.0.25.2" destinationAddress="10.0.2.1" protocol="6" sourcePort="50000" destinationPort="49153">
      <Dscp value="0x0" packets="13949" />
    </Flow>
    <Flow flowId="6" sourceAddress="10.0.25.2" destinationAddress="10.0.3.1" protocol="6" sourcePort="50000" destinationPort="49153">
      <Dscp value="0x0" packets="13553" />
    </Flow>
    <Flow flowId="27" sourceAddress="10.0.26.2" destinationAddress="10.0.4.1" protocol="6" sourcePort="50000" destinationPort="49153">
      <Dscp value="0x0" packets="24" />
    </Flow>
    <Flow flowId="28" sourceAddress="10.0.26.2" destinationAddress="10.0.5.1" protocol="6" sourcePort="50000" destinationPort="49153">
      <Dscp value="0x0" packets="24" />
    </Flow>
    <Flow flowId="29" sourceAddress="10.0.26.2" destinationAddress="10.0.6.1" protocol="6" sourcePort="50000" destinationPort="49153">
      <Dscp value="0x0" packets="24" />
    </Flow>
    <Flow flowId="30" sourceAddress="10.0.26.2" destinationAddress="10.0.7.1" protocol="6" sourcePort="50000" destinationPort="49153">
      <Dscp value="0x0" packets="24" />
    </Flow>
    <Flow flowId="31" sourceAddress="10.0.26.2" destinationAddress="10.0.8.1" protocol="6" sourcePort="50000" destinationPort="49153">
      <Dscp value="0x0" packets="24" />
    </Flow>
    <Flow flowId="32" sourceAddress="10.0.26.2" destinationAddress="10.0.9.1" protocol="6" sourcePort="50000" destinationPort="49153">
      <Dscp value="0x0" packets="24" />
    </Flow>
    <Flow flowId="33" sourceAddress="10.0.26.2" destinationAddress="10.0.10.1" protocol="6" sourcePort="50000" destinationPort="49153">
      <Dscp value="0x0" packets="24" />
    </Flow>
    <Flow flowId="34" sourceAddress="10.0.26.2" destinationAddress="10.0.11.1" protocol="6" sourcePort="50000" destinationPort="49153">
      <Dscp value="0x0" packets="24" />
    </Flow>
    <Flow flowId="35" sourceAddress="10.0.26.2" destinationAddress="10.0.12.1" protocol="6" sourcePort="50000" destinationPort="49153">
      <Dscp value="0x0" packets="24" />
    </Flow>
    <Flow flowId="36" sourceAddress="10.0.26.2" destinationAddress="10.0.13.1" protocol="6" sourcePort="50000" destinationPort="49153">
      <Dscp value="0x0" packets="24" />
    </Flow>
    <Flow flowId="37" sourceAddress="10.0.26.2" destinationAddress="10.0.14.1" protocol="6" sourcePort="50000" destinationPort="49153">
      <Dscp value="0x0" packets="24" />
    </Flow>
    <Flow flowId="38" sourceAddress="10.0.26.2" destinationAddress="10.0.15.1" protocol="6" sourcePort="50000" destinationPort="49153">
      <Dscp value="0x0" packets="24" />
    </Flow>
    <Flow flowId="39" sourceAddress="10.0.26.2" destinationAddress="10.0.16.1" protocol="6" sourcePort="50000" destinationPort="49153">
      <Dscp value="0x0" packets="24" />
    </Flow>
    <Flow flowId="40" sourceAddress="10.0.26.2" destinationAddress="10.0.17.1" protocol="6" sourcePort="50000" destinationPort="49153">
      <Dscp value="0x0" packets="24" />
    </Flow>
    <Flow flowId="41" sourceAddress="10.0.26.2" destinationAddress="10.0.18.1" protocol="6" sourcePort="50000" destinationPort="49153">
      <Dscp value="0x0" packets="24" />
    </Flow>
    <Flow flowId="42" sourceAddress="10.0.26.2" destinationAddress="10.0.19.1" protocol="6" sourcePort="50000" destinationPort="49153">
      <Dscp value="0x0" packets="24" />
    </Flow>
    <Flow flowId="43" sourceAddress="10.0.26.2" destinationAddress="10.0.20.1" protocol="6" sourcePort="50000" destinationPort="49153">
      <Dscp value="0x0" packets="24" />
    </Flow>
    <Flow flowId="44" sourceAddress="10.0.26.2" destinationAddress="10.0.21.1" protocol="6" sourcePort="50000" destinationPort="49153">
      <Dscp value="0x0" packets="24" />
    </Flow>
    <Flow flowId="45" sourceAddress="10.0.26.2" destinationAddress="10.0.22.1" protocol="6" sourcePort="50000" destinationPort="49153">
      <Dscp value="0x0" packets="24" />
    </Flow>
    <Flow flowId="46" sourceAddress="10.0.26.2" destinationAddress="10.0.23.1" protocol="6" sourcePort="50000" destinationPort="49153">
      <Dscp value="0x0" packets="24" />
    </Flow>
  </Ipv4FlowClassifier>
  <Ipv6FlowClassifier>
  </Ipv6FlowClassifier>
  <FlowProbes>
    <FlowProbe index="0">
      <FlowStats  flowId="1" packets="13562" bytes="20340088" delayFromFirstProbeSum="+153736020.0ns" >
      </FlowStats>
      <FlowStats  flowId="2" packets="14007" bytes="21007588" delayFromFirstProbeSum="+157854544.0ns" >
      </FlowStats>
      <FlowStats  flowId="3" packets="13643" bytes="20461588" delayFromFirstProbeSum="+153557597.0ns" >
      </FlowStats>
      <FlowStats  flowId="4" packets="13491" bytes="539648" delayFromFirstProbeSum="+270710418.0ns" >
      </FlowStats>
      <FlowStats  flowId="5" packets="13934" bytes="557368" delayFromFirstProbeSum="+279599656.0ns" >
      </FlowStats>
      <FlowStats  flowId="6" packets="13553" bytes="542128" delayFromFirstProbeSum="+271954510.0ns" >
      </FlowStats>
      <FlowStats  flowId="7" packets="25" bytes="33008" delayFromFirstProbeSum="+281299.0ns" >
      </FlowStats>
      <FlowStats  flowId="8" packets="25" bytes="33008" delayFromFirstProbeSum="+281299.0ns" >
      </FlowStats>
      <FlowStats  flowId="9" packets="25" bytes="33008" delayFromFirstProbeSum="+281299.0ns" >
      </FlowStats>
      <FlowStats  flowId="10" packets="25" bytes="33008" delayFromFirstProbeSum="+281299.0ns" >
      </FlowStats>
      <FlowStats  flowId="11" packets="25" bytes="33008" delayFromFirstProbeSum="+281299.0ns" >
      </FlowStats>
      <FlowStats  flowId="12" packets="25" bytes="33008" delayFromFirstProbeSum="+281299.0ns" >
      </FlowStats>
      <FlowStats  flowId="13" packets="25" bytes="33008" delayFromFirstProbeSum="+281299.0ns" >
      </FlowStats>
      <FlowStats  flowId="14" packets="25" bytes="33008" delayFromFirstProbeSum="+281299.0ns" >
      </FlowStats>
      <FlowStats  flowId="15" packets="25" bytes="33008" delayFromFirstProbeSum="+281299.0ns" >
      </FlowStats>
      <FlowStats  flowId="16" packets="25" bytes="33008" delayFromFirstProbeSum="+281299.0ns" >
      </FlowStats>
      <FlowStats  flowId="17" packets="25" bytes="33008" delayFromFirstProbeSum="+281299.0ns" >
      </FlowStats>
      <FlowStats  flowId="18" packets="25" bytes="33008" delayFromFirstProbeSum="+281299.0ns" >
      </FlowStats>
      <FlowStats  flowId="19" packets="25" bytes="33008" delayFromFirstProbeSum="+281299.0ns" >
      </FlowStats>
      <FlowStats  flowId="20" packets="25" bytes="33008" delayFromFirstProbeSum="+281299.0ns" >
      </FlowStats>
      <FlowStats  flowId="21" packets="25" bytes="33008" delayFromFirstProbeSum="+281299.0ns" >
      </FlowStats>
      <FlowStats  flowId="22" packets="25" bytes="33008" delayFromFirstProbeSum="+281299.0ns" >
      </FlowStats>
      <FlowStats  flowId="23" packets="25" bytes="33008" delayFromFirstProbeSum="+281299.0ns" >
      </FlowStats>
      <FlowStats  flowId="24" packets="25" bytes="33008" delayFromFirstProbeSum="+281299.0ns" >
      </FlowStats>
      <FlowStats  flowId="25" packets="25" bytes="33008" delayFromFirstProbeSum="+281299.0ns" >
      </FlowStats>
      <FlowStats  flowId="26" packets="25" bytes="33008" delayFromFirstProbeSum="+281299.0ns" >
      </FlowStats>
      <FlowStats  flowId="27" packets="24" bytes="968" delayFromFirstProbeSum="+481629.0ns" >
      </FlowStats>
      <FlowStats  flowId="28" packets="24" bytes="968" delayFromFirstProbeSum="+481629.0ns" >
      </FlowStats>
      <FlowStats  flowId="29" packets="24" bytes="968" delayFromFirstProbeSum="+481629.0ns" >
      </FlowStats>
      <FlowStats  flowId="30" packets="24" bytes="968" delayFromFirstProbeSum="+481629.0ns" >
      </FlowStats>
      <FlowStats  flowId="31" packets="24" bytes="968" delayFromFirstProbeSum="+481629.0ns" >
      </FlowStats>
      <FlowStats  flowId="32" packets="24" bytes="968" delayFromFirstProbeSum="+481629.0ns" >
      </FlowStats>
      <FlowStats  flowId="33" packets="24" bytes="968" delayFromFirstProbeSum="+481629.0ns" >
      </FlowStats>
      <FlowStats  flowId="34" packets="24" bytes="968" delayFromFirstProbeSum="+481629.0ns" >
      </FlowStats>
      <FlowStats  flowId="35" packets="24" bytes="968" delayFromFirstProbeSum="+481629.0ns" >
      </FlowStats>
      <FlowStats  flowId="36" packets="24" bytes="968" delayFromFirstProbeSum="+481629.0ns" >
      </FlowStats>
      <FlowStats  flowId="37" packets="24" bytes="968" delayFromFirstProbeSum="+481629.0ns" >
      </FlowStats>
      <FlowStats  flowId="38" packets="24" bytes="968" delayFromFirstProbeSum="+481629.0ns" >
      </FlowStats>
      <FlowStats  flowId="39" packets="24" bytes="968" delayFromFirstProbeSum="+481629.0ns" >
      </FlowStats>
      <FlowStats  flowId="40" packets="24" bytes="968" delayFromFirstProbeSum="+481629.0ns" >
      </FlowStats>
      <FlowStats  flowId="41" packets="24" bytes="968" delayFromFirstProbeSum="+481629.0ns" >
      </FlowStats>
      <FlowStats  flowId="42" packets="24" bytes="968" delayFromFirstProbeSum="+481629.0ns" >
      </FlowStats>
      <FlowStats  flowId="43" packets="24" bytes="968" delayFromFirstProbeSum="+481629.0ns" >
      </FlowStats>
      <FlowStats  flowId="44" packets="24" bytes="968" delayFromFirstProbeSum="+481629.0ns" >
      </FlowStats>
      <FlowStats  flowId="45" packets="24" bytes="968" delayFromFirstProbeSum="+481629.0ns" >
      </FlowStats>
      <FlowStats  flowId="46" packets="24" bytes="968" delayFromFirstProbeSum="+481629.0ns" >
      </FlowStats>
    </FlowProbe>
    <FlowProbe index="1">
    </FlowProbe>
    <FlowProbe index="2">
      <FlowStats  flowId="1" packets="13495" bytes="20239588" delayFromFirstProbeSum="+3295565919.0ns" >
      </FlowStats>
      <FlowStats  flowId="2" packets="13958" bytes="20934088" delayFromFirstProbeSum="+3412000912.0ns" >
      </FlowStats>
      <FlowStats  flowId="3" packets="13554" bytes="20328088" delayFromFirstProbeSum="+3330844145.0ns" >
      </FlowStats>
      <FlowStats  flowId="4" packets="13493" bytes="539728" delayFromFirstProbeSum="+135375275.0ns" >
      </FlowStats>
      <FlowStats  flowId="5" packets="13941" bytes="557648" delayFromFirstProbeSum="+139870059.0ns" >
      </FlowStats>
      <FlowStats  flowId="6" packets="13553" bytes="542128" delayFromFirstProbeSum="+135977255.0ns" >
      </FlowStats>
      <FlowStats  flowId="7" packets="25" bytes="33008" delayFromFirstProbeSum="+6881859.0ns" >
      </FlowStats>
      <FlowStats  flowId="8" packets="25" bytes="33008" delayFromFirstProbeSum="+6885450.0ns" >
      </FlowStats>
      <FlowStats  flowId="9" packets="25" bytes="33008" delayFromFirstProbeSum="+6893557.0ns" >
      </FlowStats>
      <FlowStats  flowId="10" packets="25" bytes="33008" delayFromFirstProbeSum="+6899358.0ns" >
      </FlowStats>
      <FlowStats  flowId="11" packets="25" bytes="33008" delayFromFirstProbeSum="+6905159.0ns" >
      </FlowStats>
      <FlowStats  flowId="12" packets="25" bytes="33008" delayFromFirstProbeSum="+6910960.0ns" >
      </FlowStats>
      <FlowStats  flowId="13" packets="25" bytes="33008" delayFromFirstProbeSum="+6916761.0ns" >
      </FlowStats>
      <FlowStats  flowId="14" packets="25" bytes="33008" delayFromFirstProbeSum="+6922562.0ns" >
      </FlowStats>
      <FlowStats  flowId="15" packets="25" bytes="33008" delayFromFirstProbeSum="+6928363.0ns" >
      </FlowStats>
      <FlowStats  flowId="16" packets="25" bytes="33008" delayFromFirstProbeSum="+6934164.0ns" >
      </FlowStats>
      <FlowStats  flowId="17" packets="25" bytes="33008" delayFromFirstProbeSum="+6939965.0ns" >
      </FlowStats>
      <FlowStats  flowId="18" packets="25" bytes="33008" delayFromFirstProbeSum="+6945766.0ns" >
      </FlowStats>
      <FlowStats  flowId="19" packets="25" bytes="33008" delayFromFirstProbeSum="+6951567.0ns" >
      </FlowStats>
      <FlowStats  flowId="20" packets="25" bytes="33008" delayFromFirstProbeSum="+6957368.0ns" >
      </FlowStats>
      <FlowStats  flowId="21" packets="25" bytes="33008" delayFromFirstProbeSum="+6963169.0ns" >
      </FlowStats>
      <FlowStats  flowId="22" packets="25" bytes="33008" delayFromFirstProbeSum="+6968970.0ns" >
      </FlowStats>
      <FlowStats  flowId="23" packets="25" bytes="33008" delayFromFirstProbeSum="+6974771.0ns" >
      </FlowStats>
      <FlowStats  flowId="24" packets="25" bytes="33008" delayFromFirstProbeSum="+6980572.0ns" >
      </FlowStats>
      <FlowStats  flowId="25" packets="25" bytes="33008" delayFromFirstProbeSum="+6986373.0ns" >
      </FlowStats>
      <FlowStats  flowId="26" packets="25" bytes="33008" delayFromFirstProbeSum="+6990973.0ns" >
      </FlowStats>
      <FlowStats  flowId="27" packets="24" bytes="968" delayFromFirstProbeSum="+240831.0ns" >
      </FlowStats>
      <FlowStats  flowId="28" packets="24" bytes="968" delayFromFirstProbeSum="+240831.0ns" >
      </FlowStats>
      <FlowStats  flowId="29" packets="24" bytes="968" delayFromFirstProbeSum="+240831.0ns" >
      </FlowStats>
      <FlowStats  flowId="30" packets="24" bytes="968" delayFromFirstProbeSum="+240831.0ns" >
      </FlowStats>
      <FlowStats  flowId="31" packets="24" bytes="968" delayFromFirstProbeSum="+240831.0ns" >
      </FlowStats>
      <FlowStats  flowId="32" packets="24" bytes="968" delayFromFirstProbeSum="+240831.0ns" >
      </FlowStats>
      <FlowStats  flowId="33" packets="24" bytes="968" delayFromFirstProbeSum="+240831.0ns" >
      </FlowStats>
      <FlowStats  flowId="34" packets="24" bytes="968" delayFromFirstProbeSum="+240831.0ns" >
      </FlowStats>
      <FlowStats  flowId="35" packets="24" bytes="968" delayFromFirstProbeSum="+240831.0ns" >
      </FlowStats>
      <FlowStats  flowId="36" packets="24" bytes="968" delayFromFirstProbeSum="+240831.0ns" >
      </FlowStats>
      <FlowStats  flowId="37" packets="24" bytes="968" delayFromFirstProbeSum="+240831.0ns" >
      </FlowStats>
      <FlowStats  flowId="38" packets="24" bytes="968" delayFromFirstProbeSum="+240831.0ns" >
      </FlowStats>
      <FlowStats  flowId="39" packets="24" bytes="968" delayFromFirstProbeSum="+240831.0ns" >
      </FlowStats>
      <FlowStats  flowId="40" packets="24" bytes="968" delayFromFirstProbeSum="+240831.0ns" >
      </FlowStats>
      <FlowStats  flowId="41" packets="24" bytes="968" delayFromFirstProbeSum="+240831.0ns" >
      </FlowStats>
      <FlowStats  flowId="42" packets="24" bytes="968" delayFromFirstProbeSum="+240831.0ns" >
      </FlowStats>
      <FlowStats  flowId="43" packets="24" bytes="968" delayFromFirstProbeSum="+240831.0ns" >
      </FlowStats>
      <FlowStats  flowId="44" packets="24" bytes="968" delayFromFirstProbeSum="+240831.0ns" >
      </FlowStats>
      <FlowStats  flowId="45" packets="24" bytes="968" delayFromFirstProbeSum="+240831.0ns" >
      </FlowStats>
      <FlowStats  flowId="46" packets="24" bytes="968" delayFromFirstProbeSum="+240831.0ns" >
      </FlowStats>
    </FlowProbe>
    <FlowProbe index="3">
    </FlowProbe>
    <FlowProbe index="4">
      <FlowStats  flowId="1" packets="13568" bytes="20349088" delayFromFirstProbeSum="+0.0ns" >
      </FlowStats>
      <FlowStats  flowId="4" packets="13490" bytes="539608" delayFromFirstProbeSum="+406035528.0ns" >
      </FlowStats>
    </FlowProbe>
    <FlowProbe index="5">
    </FlowProbe>
    <FlowProbe index="6">
      <FlowStats  flowId="2" packets="14010" bytes="21012088" delayFromFirstProbeSum="+0.0ns" >
      </FlowStats>
      <FlowStats  flowId="5" packets="13927" bytes="557088" delayFromFirstProbeSum="+419188791.0ns" >
      </FlowStats>
    </FlowProbe>
    <FlowProbe index="7">
    </FlowProbe>
    <FlowProbe index="8">
      <FlowStats  flowId="3" packets="13643" bytes="20461588" delayFromFirstProbeSum="+0.0ns" >
      </FlowStats>
      <FlowStats  flowId="6" packets="13553" bytes="542128" delayFromFirstProbeSum="+407931765.0ns" >
      </FlowStats>
    </FlowProbe>
    <FlowProbe index="9">
    </FlowProbe>
    <FlowProbe index="10">
      <FlowStats  flowId="7" packets="25" bytes="33008" delayFromFirstProbeSum="+0.0ns" >
      </FlowStats>
      <FlowStats  flowId="27" packets="24" bytes="968" delayFromFirstProbeSum="+722427.0ns" >
      </FlowStats>
    </FlowProbe>
    <FlowProbe index="11">
    </FlowProbe>
    <FlowProbe index="12">
      <FlowStats  flowId="8" packets="25" bytes="33008" delayFromFirstProbeSum="+0.0ns" >
      </FlowStats>
      <FlowStats  flowId="28" packets="24" bytes="968" delayFromFirstProbeSum="+722427.0ns" >
      </FlowStats>
    </FlowProbe>
    <FlowProbe index="13">
    </FlowProbe>
    <FlowProbe index="14">
      <FlowStats  flowId="9" packets="25" bytes="33008" delayFromFirstProbeSum="+0.0ns" >
      </FlowStats>
      <FlowStats  flowId="29" packets="24" bytes="968" delayFromFirstProbeSum="+722427.0ns" >
      </FlowStats>
    </FlowProbe>
    <FlowProbe index="15">
    </FlowProbe>
    <FlowProbe index="16">
      <FlowStats  flowId="10" packets="25" bytes="33008" delayFromFirstProbeSum="+0.0ns" >
      </FlowStats>
      <FlowStats  flowId="30" packets="24" bytes="968" delayFromFirstProbeSum="+722427.0ns" >
      </FlowStats>
    </FlowProbe>
    <FlowProbe index="17">
    </FlowProbe>
    <FlowProbe index="18">
      <FlowStats  flowId="11" packets="25" bytes="33008" delayFromFirstProbeSum="+0.0ns" >
      </FlowStats>
      <FlowStats  flowId="31" packets="24" bytes="968" delayFromFirstProbeSum="+722427.0ns" >
      </FlowStats>
    </FlowProbe>
    <FlowProbe index="19">
    </FlowProbe>
    <FlowProbe index="20">
      <FlowStats  flowId="12" packets="25" bytes="33008" delayFromFirstProbeSum="+0.0ns" >
      </FlowStats>
      <FlowStats  flowId="32" packets="24" bytes="968" delayFromFirstProbeSum="+722427.0ns" >
      </FlowStats>
    </FlowProbe>
    <FlowProbe index="21">
    </FlowProbe>
    <FlowProbe index="22">
      <FlowStats  flowId="13" packets="25" bytes="33008" delayFromFirstProbeSum="+0.0ns" >
      </FlowStats>
      <FlowStats  flowId="33" packets="24" bytes="968" delayFromFirstProbeSum="+722427.0ns" >
      </FlowStats>
    </FlowProbe>
    <FlowProbe index="23">
    </FlowProbe>
    <FlowProbe index="24">
      <FlowStats  flowId="14" packets="25" bytes="33008" delayFromFirstProbeSum="+0.0ns" >
      </FlowStats>
      <FlowStats  flowId="34" packets="24" bytes="968" delayFromFirstProbeSum="+722427.0ns" >
      </FlowStats>
    </FlowProbe>
    <FlowProbe index="25">
    </FlowProbe>
    <FlowProbe index="26">
      <FlowStats  flowId="15" packets="25" bytes="33008" delayFromFirstProbeSum="+0.0ns" >
      </FlowStats>
      <FlowStats  flowId="35" packets="24" bytes="968" delayFromFirstProbeSum="+722427.0ns" >
      </FlowStats>
    </FlowProbe>
    <FlowProbe index="27">
    </FlowProbe>
    <FlowProbe index="28">
      <FlowStats  flowId="16" packets="25" bytes="33008" delayFromFirstProbeSum="+0.0ns" >
      </FlowStats>
      <FlowStats  flowId="36" packets="24" bytes="968" delayFromFirstProbeSum="+722427.0ns" >
      </FlowStats>
    </FlowProbe>
    <FlowProbe index="29">
    </FlowProbe>
    <FlowProbe index="30">
      <FlowStats  flowId="17" packets="25" bytes="33008" delayFromFirstProbeSum="+0.0ns" >
      </FlowStats>
      <FlowStats  flowId="37" packets="24" bytes="968" delayFromFirstProbeSum="+722427.0ns" >
      </FlowStats>
    </FlowProbe>
    <FlowProbe index="31">
    </FlowProbe>
    <FlowProbe index="32">
      <FlowStats  flowId="18" packets="25" bytes="33008" delayFromFirstProbeSum="+0.0ns" >
      </FlowStats>
      <FlowStats  flowId="38" packets="24" bytes="968" delayFromFirstProbeSum="+722427.0ns" >
      </FlowStats>
    </FlowProbe>
    <FlowProbe index="33">
    </FlowProbe>
    <FlowProbe index="34">
      <FlowStats  flowId="19" packets="25" bytes="33008" delayFromFirstProbeSum="+0.0ns" >
      </FlowStats>
      <FlowStats  flowId="39" packets="24" bytes="968" delayFromFirstProbeSum="+722427.0ns" >
      </FlowStats>
    </FlowProbe>
    <FlowProbe index="35">
    </FlowProbe>
    <FlowProbe index="36">
      <FlowStats  flowId="20" packets="25" bytes="33008" delayFromFirstProbeSum="+0.0ns" >
      </FlowStats>
      <FlowStats  flowId="40" packets="24" bytes="968" delayFromFirstProbeSum="+722427.0ns" >
      </FlowStats>
    </FlowProbe>
    <FlowProbe index="37">
    </FlowProbe>
    <FlowProbe index="38">
      <FlowStats  flowId="21" packets="25" bytes="33008" delayFromFirstProbeSum="+0.0ns" >
      </FlowStats>
      <FlowStats  flowId="41" packets="24" bytes="968" delayFromFirstProbeSum="+722427.0ns" >
      </FlowStats>
    </FlowProbe>
    <FlowProbe index="39">
    </FlowProbe>
    <FlowProbe index="40">
      <FlowStats  flowId="22" packets="25" bytes="33008" delayFromFirstProbeSum="+0.0ns" >
      </FlowStats>
      <FlowStats  flowId="42" packets="24" bytes="968" delayFromFirstProbeSum="+722427.0ns" >
      </FlowStats>
    </FlowProbe>
    <FlowProbe index="41">
    </FlowProbe>
    <FlowProbe index="42">
      <FlowStats  flowId="23" packets="25" bytes="33008" delayFromFirstProbeSum="+0.0ns" >
      </FlowStats>
      <FlowStats  flowId="43" packets="24" bytes="968" delayFromFirstProbeSum="+722427.0ns" >
      </FlowStats>
    </FlowProbe>
    <FlowProbe index="43">
    </FlowProbe>
    <FlowProbe index="44">
      <FlowStats  flowId="24" packets="25" bytes="33008" delayFromFirstProbeSum="+0.0ns" >
      </FlowStats>
      <FlowStats  flowId="44" packets="24" bytes="968" delayFromFirstProbeSum="+722427.0ns" >
      </FlowStats>
    </FlowProbe>
    <FlowProbe index="45">
    </FlowProbe>
    <FlowProbe index="46">
      <FlowStats  flowId="25" packets="25" bytes="33008" delayFromFirstProbeSum="+0.0ns" >
      </FlowStats>
      <FlowStats  flowId="45" packets="24" bytes="968" delayFromFirstProbeSum="+722427.0ns" >
      </FlowStats>
    </FlowProbe>
    <FlowProbe index="47">
    </FlowProbe>
    <FlowProbe index="48">
      <FlowStats  flowId="26" packets="25" bytes="33008" delayFromFirstProbeSum="+0.0ns" >
      </FlowStats>
      <FlowStats  flowId="46" packets="24" bytes="968" delayFromFirstProbeSum="+722427.0ns" >
      </FlowStats>
    </FlowProbe>
    <FlowProbe index="49">
    </FlowProbe>
    <FlowProbe index="50">
      <FlowStats  flowId="1" packets="13494" bytes="20238088" delayFromFirstProbeSum="+3446455737.0ns" >
      </FlowStats>
      <FlowStats  flowId="2" packets="13950" bytes="20922088" delayFromFirstProbeSum="+3566209756.0ns" >
      </FlowStats>
      <FlowStats  flowId="3" packets="13554" bytes="20328088" delayFromFirstProbeSum="+3482660169.0ns" >
      </FlowStats>
      <FlowStats  flowId="4" packets="13493" bytes="539728" delayFromFirstProbeSum="+0.0ns" >
      </FlowStats>
      <FlowStats  flowId="5" packets="13949" bytes="557968" delayFromFirstProbeSum="+0.0ns" >
      </FlowStats>
      <FlowStats  flowId="6" packets="13553" bytes="542128" delayFromFirstProbeSum="+0.0ns" >
      </FlowStats>
    </FlowProbe>
    <FlowProbe index="51">
    </FlowProbe>
    <FlowProbe index="52">
      <FlowStats  flowId="7" packets="25" bytes="33008" delayFromFirstProbeSum="+7158386.0ns" >
      </FlowStats>
      <FlowStats  flowId="8" packets="25" bytes="33008" delayFromFirstProbeSum="+7161977.0ns" >
      </FlowStats>
      <FlowStats  flowId="9" packets="25" bytes="33008" delayFromFirstProbeSum="+7170084.0ns" >
      </FlowStats>
      <FlowStats  flowId="10" packets="25" bytes="33008" delayFromFirstProbeSum="+7175885.0ns" >
      </FlowStats>
      <FlowStats  flowId="11" packets="25" bytes="33008" delayFromFirstProbeSum="+7181686.0ns" >
      </FlowStats>
      <FlowStats  flowId="12" packets="25" bytes="33008" delayFromFirstProbeSum="+7187487.0ns" >
      </FlowStats>
      <FlowStats  flowId="13" packets="25" bytes="33008" delayFromFirstProbeSum="+7193288.0ns" >
      </FlowStats>
      <FlowStats  flowId="14" packets="25" bytes="33008" delayFromFirstProbeSum="+7199089.0ns" >
      </FlowStats>
      <FlowStats  flowId="15" packets="25" bytes="33008" delayFromFirstProbeSum="+7204890.0ns" >
      </FlowStats>
      <FlowStats  flowId="16" packets="25" bytes="33008" delayFromFirstProbeSum="+7210691.0ns" >
      </FlowStats>
      <FlowStats  flowId="17" packets="25" bytes="33008" delayFromFirstProbeSum="+7216492.0ns" >
      </FlowStats>
      <FlowStats  flowId="18" packets="25" bytes="33008" delayFromFirstProbeSum="+7222293.0ns" >
      </FlowStats>
      <FlowStats  flowId="19" packets="25" bytes="33008" delayFromFirstProbeSum="+7228094.0ns" >
      </FlowStats>
      <FlowStats  flowId="20" packets="25" bytes="33008" delayFromFirstProbeSum="+7233895.0ns" >
      </FlowStats>
      <FlowStats  flowId="21" packets="25" bytes="33008" delayFromFirstProbeSum="+7239696.0ns" >
      </FlowStats>
      <FlowStats  flowId="22" packets="25" bytes="33008" delayFromFirstProbeSum="+7245497.0ns" >
      </FlowStats>
      <FlowStats  flowId="23" packets="25" bytes="33008" delayFromFirstProbeSum="+7251298.0ns" >
      </FlowStats>
      <FlowStats  flowId="24" packets="25" bytes="33008" delayFromFirstProbeSum="+7257099.0ns" >
      </FlowStats>
      <FlowStats  flowId="25" packets="25" bytes="33008" delayFromFirstProbeSum="+7262900.0ns" >
      </FlowStats>
      <FlowStats  flowId="26" packets="25" bytes="33008" delayFromFirstProbeSum="+7267500.0ns" >
      </FlowStats>
      <FlowStats  flowId="27" packets="24" bytes="968" delayFromFirstProbeSum="+0.0ns" >
      </FlowStats>
      <FlowStats  flowId="28" packets="24" bytes="968" delayFromFirstProbeSum="+0.0ns" >
      </FlowStats>
      <FlowStats  flowId="29" packets="24" bytes="968" delayFromFirstProbeSum="+0.0ns" >
      </FlowStats>
      <FlowStats  flowId="30" packets="24" bytes="968" delayFromFirstProbeSum="+0.0ns" >
      </FlowStats>
      <FlowStats  flowId="31" packets="24" bytes="968" delayFromFirstProbeSum="+0.0ns" >
      </FlowStats>
      <FlowStats  flowId="32" packets="24" bytes="968" delayFromFirstProbeSum="+0.0ns" >
      </FlowStats>
      <FlowStats  flowId="33" packets="24" bytes="968" delayFromFirstProbeSum="+0.0ns" >
      </FlowStats>
      <FlowStats  flowId="34" packets="24" bytes="968" delayFromFirstProbeSum="+0.0ns" >
      </FlowStats>
      <FlowStats  flowId="35" packets="24" bytes="968" delayFromFirstProbeSum="+0.0ns" >
      </FlowStats>
      <FlowStats  flowId="36" packets="24" bytes="968" delayFromFirstProbeSum="+0.0ns" >
      </FlowStats>
      <FlowStats  flowId="37" packets="24" bytes="968" delayFromFirstProbeSum="+0.0ns" >
      </FlowStats>
      <FlowStats  flowId="38" packets="24" bytes="968" delayFromFirstProbeSum="+0.0ns" >
      </FlowStats>
      <FlowStats  flowId="39" packets="24" bytes="968" delayFromFirstProbeSum="+0.0ns" >
      </FlowStats>
      <FlowStats  flowId="40" packets="24" bytes="968" delayFromFirstProbeSum="+0.0ns" >
      </FlowStats>
      <FlowStats  flowId="41" packets="24" bytes="968" delayFromFirstProbeSum="+0.0ns" >
      </FlowStats>
      <FlowStats  flowId="42" packets="24" bytes="968" delayFromFirstProbeSum="+0.0ns" >
      </FlowStats>
      <FlowStats  flowId="43" packets="24" bytes="968" delayFromFirstProbeSum="+0.0ns" >
      </FlowStats>
      <FlowStats  flowId="44" packets="24" bytes="968" delayFromFirstProbeSum="+0.0ns" >
      </FlowStats>
      <FlowStats  flowId="45" packets="24" bytes="968" delayFromFirstProbeSum="+0.0ns" >
      </FlowStats>
      <FlowStats  flowId="46" packets="24" bytes="968" delayFromFirstProbeSum="+0.0ns" >
      </FlowStats>
    </FlowProbe>
    <FlowProbe index="53">
    </FlowProbe>
  </FlowProbes>
</FlowMonitor>
