<?xml version="1.0" ?>
<FlowMonitor>
  <FlowStats>
    <Flow flowId="1" timeFirstTxPacket="+0.0ns" timeFirstRxPacket="+30117.0ns" timeLastTxPacket="+49988711.0ns" timeLastRxPacket="+49958612.0ns" delaySum="+2989008582.0ns" jitterSum="+2402686.0ns" lastDelay="+222111.0ns" txBytes="21093088" rxBytes="20980588" txPackets="14064" rxPackets="13989" lostPackets="0" timesForwarded="27978">
      <delayHistogram nBins="1" >
        <bin index="0" start="0" width="0.001" count="13989" />
      </delayHistogram>
      <jitterHistogram nBins="1" >
        <bin index="0" start="0" width="0.001" count="13988" />
      </jitterHistogram>
      <packetSizeHistogram nBins="76" >
        <bin index="2" start="40" width="20" count="2" />
        <bin index="75" start="1500" width="20" count="13987" />
      </packetSizeHistogram>
      <flowInterruptionsHistogram nBins="0" >
      </flowInterruptionsHistogram>
    </Flow>
    <Flow flowId="2" timeFirstTxPacket="+0.0ns" timeFirstRxPacket="+30156.0ns" timeLastTxPacket="+49999520.0ns" timeLastRxPacket="+49998245.0ns" delaySum="+2875176146.0ns" jitterSum="+2549307.0ns" lastDelay="+222111.0ns" txBytes="20113588" rxBytes="20040088" txPackets="13411" rxPackets="13362" lostPackets="0" timesForwarded="26724">
      <delayHistogram nBins="1" >
        <bin index="0" start="0" width="0.001" count="13362" />
      </delayHistogram>
      <jitterHistogram nBins="1" >
        <bin index="0" start="0" width="0.001" count="13361" />
      </jitterHistogram>
      <packetSizeHistogram nBins="76" >
        <bin index="2" start="40" width="20" count="2" />
        <bin index="75" start="1500" width="20" count="13360" />
      </packetSizeHistogram>
      <flowInterruptionsHistogram nBins="0" >
      </flowInterruptionsHistogram>
    </Flow>
    <Flow flowId="3" timeFirstTxPacket="+0.0ns" timeFirstRxPacket="+30195.0ns" timeLastTxPacket="+49979103.0ns" timeLastRxPacket="+49999446.0ns" delaySum="+2768548742.0ns" jitterSum="+2282508.0ns" lastDelay="+222111.0ns" txBytes="19576588" rxBytes="19480588" txPackets="13053" rxPackets="12989" lostPackets="0" timesForwarded="25978">
      <delayHistogram nBins="1" >
        <bin index="0" start="0" width="0.001" count="12989" />
      </delayHistogram>
      <jitterHistogram nBins="1" >
        <bin index="0" start="0" width="0.001" count="12988" />
      </jitterHistogram>
      <packetSizeHistogram nBins="76" >
        <bin index="2" start="40" width="20" count="2" />
        <bin index="75" start="1500" width="20" count="12987" />
      </packetSizeHistogram>
      <flowInterruptionsHistogram nBins="0" >
      </flowInterruptionsHistogram>
    </Flow>
    <Flow flowId="4" timeFirstTxPacket="+30117.0ns" timeFirstRxPacket="+60234.0ns" timeLastTxPacket="+49958612.0ns" timeLastRxPacket="+49988711.0ns" delaySum="+421024830.0ns" jitterSum="+18.0ns" lastDelay="+30099.0ns" txBytes="559528" rxBytes="559528" txPackets="13988" rxPackets="13988" lostPackets="0" timesForwarded="27976">
      <delayHistogram nBins="1" >
        <bin index="0" start="0" width="0.001" count="13988" />
      </delayHistogram>
      <jitterHistogram nBins="1" >
        <bin index="0" start="0" width="0.001" count="13987" />
      </jitterHistogram>
      <packetSizeHistogram nBins="3" >
        <bin index="2" start="40" width="20" count="13988" />
      </packetSizeHistogram>
      <flowInterruptionsHistogram nBins="0" >
      </flowInterruptionsHistogram>
    </Flow>
    <Flow flowId="5" timeFirstTxPacket="+30156.0ns" timeFirstRxPacket="+60273.0ns" timeLastTxPacket="+49998245.0ns" timeLastRxPacket="+49999520.0ns" delaySum="+401520678.0ns" jitterSum="+18.0ns" lastDelay="+30099.0ns" txBytes="534448" rxBytes="533608" txPackets="13361" rxPackets="13340" lostPackets="0" timesForwarded="26680">
      <delayHistogram nBins="1" >
        <bin index="0" start="0" width="0.001" count="13340" />
      </delayHistogram>
      <jitterHistogram nBins="1" >
        <bin index="0" start="0" width="0.001" count="13339" />
      </jitterHistogram>
      <packetSizeHistogram nBins="3" >
        <bin index="2" start="40" width="20" count="13340" />
      </packetSizeHistogram>
      <flowInterruptionsHistogram nBins="0" >
      </flowInterruptionsHistogram>
    </Flow>
    <Flow flowId="6" timeFirstTxPacket="+30195.0ns" timeFirstRxPacket="+60312.0ns" timeLastTxPacket="+49999446.0ns" timeLastRxPacket="+49979103.0ns" delaySum="+390805434.0ns" jitterSum="+18.0ns" lastDelay="+30099.0ns" txBytes="519528" rxBytes="519368" txPackets="12988" rxPackets="12984" lostPackets="0" timesForwarded="25968">
      <delayHistogram nBins="1" >
        <bin index="0" start="0" width="0.001" count="12984" />
      </delayHistogram>
      <jitterHistogram nBins="1" >
        <bin index="0" start="0" width="0.001" count="12983" />
      </jitterHistogram>
      <packetSizeHistogram nBins="3" >
        <bin index="2" start="40" width="20" count="12984" />
      </packetSizeHistogram>
      <flowInterruptionsHistogram nBins="0" >
      </flowInterruptionsHistogram>
    </Flow>
    <Flow flowId="7" timeFirstTxPacket="+28329157.0ns" timeFirstRxPacket="+28548236.0ns" timeLastTxPacket="+31559150.0ns" timeLastRxPacket="+31637291.0ns" delaySum="+11819499.0ns" jitterSum="+482040.0ns" lastDelay="+78141.0ns" txBytes="65888" rxBytes="65888" txPackets="47" rxPackets="47" lostPackets="0" timesForwarded="94">
      <delayHistogram nBins="1" >
        <bin index="0" start="0" width="0.001" count="47" />
      </delayHistogram>
      <jitterHistogram nBins="1" >
        <bin index="0" start="0" width="0.001" count="46" />
      </jitterHistogram>
      <packetSizeHistogram nBins="76" >
        <bin index="2" start="40" width="20" count="3" />
        <bin index="63" start="1260" width="20" count="1" />
        <bin index="75" start="1500" width="20" count="43" />
      </packetSizeHistogram>
      <flowInterruptionsHistogram nBins="0" >
      </flowInterruptionsHistogram>
    </Flow>
    <Flow flowId="8" timeFirstTxPacket="+28329157.0ns" timeFirstRxPacket="+28548275.0ns" timeLastTxPacket="+31564963.0ns" timeLastRxPacket="+31637324.0ns" delaySum="+11827318.0ns" jitterSum="+499407.0ns" lastDelay="+72361.0ns" txBytes="65888" rxBytes="65888" txPackets="47" rxPackets="47" lostPackets="0" timesForwarded="94">
      <delayHistogram nBins="1" >
        <bin index="0" start="0" width="0.001" count="47" />
      </delayHistogram>
      <jitterHistogram nBins="1" >
        <bin index="0" start="0" width="0.001" count="46" />
      </jitterHistogram>
      <packetSizeHistogram nBins="76" >
        <bin index="2" start="40" width="20" count="3" />
        <bin index="63" start="1260" width="20" count="1" />
        <bin index="75" start="1500" width="20" count="43" />
      </packetSizeHistogram>
      <flowInterruptionsHistogram nBins="0" >
      </flowInterruptionsHistogram>
    </Flow>
    <Flow flowId="9" timeFirstTxPacket="+28329157.0ns" timeFirstRxPacket="+28548314.0ns" timeLastTxPacket="+31570776.0ns" timeLastRxPacket="+31637357.0ns" delaySum="+11836146.0ns" jitterSum="+512354.0ns" lastDelay="+66581.0ns" txBytes="65888" rxBytes="65888" txPackets="47" rxPackets="47" lostPackets="0" timesForwarded="94">
      <delayHistogram nBins="1" >
        <bin index="0" start="0" width="0.001" count="47" />
      </delayHistogram>
      <jitterHistogram nBins="1" >
        <bin index="0" start="0" width="0.001" count="46" />
      </jitterHistogram>
      <packetSizeHistogram nBins="76" >
        <bin index="2" start="40" width="20" count="3" />
        <bin index="63" start="1260" width="20" count="1" />
        <bin index="75" start="1500" width="20" count="43" />
      </packetSizeHistogram>
      <flowInterruptionsHistogram nBins="0" >
      </flowInterruptionsHistogram>
    </Flow>
    <Flow flowId="10" timeFirstTxPacket="+28329157.0ns" timeFirstRxPacket="+28548353.0ns" timeLastTxPacket="+31575388.0ns" timeLastRxPacket="+31637390.0ns" delaySum="+11844974.0ns" jitterSum="+518912.0ns" lastDelay="+62002.0ns" txBytes="65888" rxBytes="65888" txPackets="47" rxPackets="47" lostPackets="0" timesForwarded="94">
      <delayHistogram nBins="1" >
        <bin index="0" start="0" width="0.001" count="47" />
      </delayHistogram>
      <jitterHistogram nBins="1" >
        <bin index="0" start="0" width="0.001" count="46" />
      </jitterHistogram>
      <packetSizeHistogram nBins="76" >
        <bin index="2" start="40" width="20" count="3" />
        <bin index="63" start="1260" width="20" count="1" />
        <bin index="75" start="1500" width="20" count="43" />
      </packetSizeHistogram>
      <flowInterruptionsHistogram nBins="0" >
      </flowInterruptionsHistogram>
    </Flow>
    <Flow flowId="11" timeFirstTxPacket="+28329157.0ns" timeFirstRxPacket="+28548392.0ns" timeLastTxPacket="+31434675.0ns" timeLastRxPacket="+31635397.0ns" delaySum="+11983678.0ns" jitterSum="+326917.0ns" lastDelay="+200722.0ns" txBytes="65888" rxBytes="65888" txPackets="47" rxPackets="47" lostPackets="0" timesForwarded="94">
      <delayHistogram nBins="1" >
        <bin index="0" start="0" width="0.001" count="47" />
      </delayHistogram>
      <jitterHistogram nBins="1" >
        <bin index="0" start="0" width="0.001" count="46" />
      </jitterHistogram>
      <packetSizeHistogram nBins="76" >
        <bin index="2" start="40" width="20" count="3" />
        <bin index="63" start="1260" width="20" count="1" />
        <bin index="75" start="1500" width="20" count="43" />
      </packetSizeHistogram>
      <flowInterruptionsHistogram nBins="0" >
      </flowInterruptionsHistogram>
    </Flow>
    <Flow flowId="12" timeFirstTxPacket="+28329157.0ns" timeFirstRxPacket="+28548431.0ns" timeLastTxPacket="+31440488.0ns" timeLastRxPacket="+31635430.0ns" delaySum="+11998703.0ns" jitterSum="+341882.0ns" lastDelay="+194942.0ns" txBytes="65888" rxBytes="65888" txPackets="47" rxPackets="47" lostPackets="0" timesForwarded="94">
      <delayHistogram nBins="1" >
        <bin index="0" start="0" width="0.001" count="47" />
      </delayHistogram>
      <jitterHistogram nBins="1" >
        <bin index="0" start="0" width="0.001" count="46" />
      </jitterHistogram>
      <packetSizeHistogram nBins="76" >
        <bin index="2" start="40" width="20" count="3" />
        <bin index="63" start="1260" width="20" count="1" />
        <bin index="75" start="1500" width="20" count="43" />
      </packetSizeHistogram>
      <flowInterruptionsHistogram nBins="0" >
      </flowInterruptionsHistogram>
    </Flow>
    <Flow flowId="13" timeFirstTxPacket="+28329157.0ns" timeFirstRxPacket="+28548470.0ns" timeLastTxPacket="+31446301.0ns" timeLastRxPacket="+31635463.0ns" delaySum="+12014737.0ns" jitterSum="+347239.0ns" lastDelay="+189162.0ns" txBytes="65888" rxBytes="65888" txPackets="47" rxPackets="47" lostPackets="0" timesForwarded="94">
      <delayHistogram nBins="1" >
        <bin index="0" start="0" width="0.001" count="47" />
      </delayHistogram>
      <jitterHistogram nBins="1" >
        <bin index="0" start="0" width="0.001" count="46" />
      </jitterHistogram>
      <packetSizeHistogram nBins="76" >
        <bin index="2" start="40" width="20" count="3" />
        <bin index="63" start="1260" width="20" count="1" />
        <bin index="75" start="1500" width="20" count="43" />
      </packetSizeHistogram>
      <flowInterruptionsHistogram nBins="0" >
      </flowInterruptionsHistogram>
    </Flow>
    <Flow flowId="14" timeFirstTxPacket="+28329157.0ns" timeFirstRxPacket="+28548509.0ns" timeLastTxPacket="+31452114.0ns" timeLastRxPacket="+31635496.0ns" delaySum="+12028369.0ns" jitterSum="+352596.0ns" lastDelay="+183382.0ns" txBytes="65888" rxBytes="65888" txPackets="47" rxPackets="47" lostPackets="0" timesForwarded="94">
      <delayHistogram nBins="1" >
        <bin index="0" start="0" width="0.001" count="47" />
      </delayHistogram>
      <jitterHistogram nBins="1" >
        <bin index="0" start="0" width="0.001" count="46" />
      </jitterHistogram>
      <packetSizeHistogram nBins="76" >
        <bin index="2" start="40" width="20" count="3" />
        <bin index="63" start="1260" width="20" count="1" />
        <bin index="75" start="1500" width="20" count="43" />
      </packetSizeHistogram>
      <flowInterruptionsHistogram nBins="0" >
      </flowInterruptionsHistogram>
    </Flow>
    <Flow flowId="15" timeFirstTxPacket="+28329157.0ns" timeFirstRxPacket="+28548548.0ns" timeLastTxPacket="+31457927.0ns" timeLastRxPacket="+31635529.0ns" delaySum="+12042001.0ns" jitterSum="+355551.0ns" lastDelay="+177602.0ns" txBytes="65888" rxBytes="65888" txPackets="47" rxPackets="47" lostPackets="0" timesForwarded="94">
      <delayHistogram nBins="1" >
        <bin index="0" start="0" width="0.001" count="47" />
      </delayHistogram>
      <jitterHistogram nBins="1" >
        <bin index="0" start="0" width="0.001" count="46" />
      </jitterHistogram>
      <packetSizeHistogram nBins="76" >
        <bin index="2" start="40" width="20" count="3" />
        <bin index="63" start="1260" width="20" count="1" />
        <bin index="75" start="1500" width="20" count="43" />
      </packetSizeHistogram>
      <flowInterruptionsHistogram nBins="0" >
      </flowInterruptionsHistogram>
    </Flow>
    <Flow flowId="16" timeFirstTxPacket="+28329157.0ns" timeFirstRxPacket="+28548587.0ns" timeLastTxPacket="+31463740.0ns" timeLastRxPacket="+31635562.0ns" delaySum="+12055633.0ns" jitterSum="+358506.0ns" lastDelay="+171822.0ns" txBytes="65888" rxBytes="65888" txPackets="47" rxPackets="47" lostPackets="0" timesForwarded="94">
      <delayHistogram nBins="1" >
        <bin index="0" start="0" width="0.001" count="47" />
      </delayHistogram>
      <jitterHistogram nBins="1" >
        <bin index="0" start="0" width="0.001" count="46" />
      </jitterHistogram>
      <packetSizeHistogram nBins="76" >
        <bin index="2" start="40" width="20" count="3" />
        <bin index="63" start="1260" width="20" count="1" />
        <bin index="75" start="1500" width="20" count="43" />
      </packetSizeHistogram>
      <flowInterruptionsHistogram nBins="0" >
      </flowInterruptionsHistogram>
    </Flow>
    <Flow flowId="17" timeFirstTxPacket="+28329157.0ns" timeFirstRxPacket="+28548626.0ns" timeLastTxPacket="+31469553.0ns" timeLastRxPacket="+31635595.0ns" delaySum="+12068064.0ns" jitterSum="+361461.0ns" lastDelay="+166042.0ns" txBytes="65888" rxBytes="65888" txPackets="47" rxPackets="47" lostPackets="0" timesForwarded="94">
      <delayHistogram nBins="1" >
        <bin index="0" start="0" width="0.001" count="47" />
      </delayHistogram>
      <jitterHistogram nBins="1" >
        <bin index="0" start="0" width="0.001" count="46" />
      </jitterHistogram>
      <packetSizeHistogram nBins="76" >
        <bin index="2" start="40" width="20" count="3" />
        <bin index="63" start="1260" width="20" count="1" />
        <bin index="75" start="1500" width="20" count="43" />
      </packetSizeHistogram>
      <flowInterruptionsHistogram nBins="0" >
      </flowInterruptionsHistogram>
    </Flow>
    <Flow flowId="18" timeFirstTxPacket="+28329157.0ns" timeFirstRxPacket="+28548665.0ns" timeLastTxPacket="+31475366.0ns" timeLastRxPacket="+31635628.0ns" delaySum="+12080495.0ns" jitterSum="+364416.0ns" lastDelay="+160262.0ns" txBytes="65888" rxBytes="65888" txPackets="47" rxPackets="47" lostPackets="0" timesForwarded="94">
      <delayHistogram nBins="1" >
        <bin index="0" start="0" width="0.001" count="47" />
      </delayHistogram>
      <jitterHistogram nBins="1" >
        <bin index="0" start="0" width="0.001" count="46" />
      </jitterHistogram>
      <packetSizeHistogram nBins="76" >
        <bin index="2" start="40" width="20" count="3" />
        <bin index="63" start="1260" width="20" count="1" />
        <bin index="75" start="1500" width="20" count="43" />
      </packetSizeHistogram>
      <flowInterruptionsHistogram nBins="0" >
      </flowInterruptionsHistogram>
    </Flow>
    <Flow flowId="19" timeFirstTxPacket="+28329157.0ns" timeFirstRxPacket="+28548704.0ns" timeLastTxPacket="+31481179.0ns" timeLastRxPacket="+31635661.0ns" delaySum="+12092926.0ns" jitterSum="+367371.0ns" lastDelay="+154482.0ns" txBytes="65888" rxBytes="65888" txPackets="47" rxPackets="47" lostPackets="0" timesForwarded="94">
      <delayHistogram nBins="1" >
        <bin index="0" start="0" width="0.001" count="47" />
      </delayHistogram>
      <jitterHistogram nBins="1" >
        <bin index="0" start="0" width="0.001" count="46" />
      </jitterHistogram>
      <packetSizeHistogram nBins="76" >
        <bin index="2" start="40" width="20" count="3" />
        <bin index="63" start="1260" width="20" count="1" />
        <bin index="75" start="1500" width="20" count="43" />
      </packetSizeHistogram>
      <flowInterruptionsHistogram nBins="0" >
      </flowInterruptionsHistogram>
    </Flow>
    <Flow flowId="20" timeFirstTxPacket="+28329157.0ns" timeFirstRxPacket="+28548743.0ns" timeLastTxPacket="+31486992.0ns" timeLastRxPacket="+31635694.0ns" delaySum="+12105357.0ns" jitterSum="+370326.0ns" lastDelay="+148702.0ns" txBytes="65888" rxBytes="65888" txPackets="47" rxPackets="47" lostPackets="0" timesForwarded="94">
      <delayHistogram nBins="1" >
        <bin index="0" start="0" width="0.001" count="47" />
      </delayHistogram>
      <jitterHistogram nBins="1" >
        <bin index="0" start="0" width="0.001" count="46" />
      </jitterHistogram>
      <packetSizeHistogram nBins="76" >
        <bin index="2" start="40" width="20" count="3" />
        <bin index="63" start="1260" width="20" count="1" />
        <bin index="75" start="1500" width="20" count="43" />
      </packetSizeHistogram>
      <flowInterruptionsHistogram nBins="0" >
      </flowInterruptionsHistogram>
    </Flow>
    <Flow flowId="21" timeFirstTxPacket="+28329157.0ns" timeFirstRxPacket="+28548782.0ns" timeLastTxPacket="+31492805.0ns" timeLastRxPacket="+31635727.0ns" delaySum="+12117788.0ns" jitterSum="+373281.0ns" lastDelay="+142922.0ns" txBytes="65888" rxBytes="65888" txPackets="47" rxPackets="47" lostPackets="0" timesForwarded="94">
      <delayHistogram nBins="1" >
        <bin index="0" start="0" width="0.001" count="47" />
      </delayHistogram>
      <jitterHistogram nBins="1" >
        <bin index="0" start="0" width="0.001" count="46" />
      </jitterHistogram>
      <packetSizeHistogram nBins="76" >
        <bin index="2" start="40" width="20" count="3" />
        <bin index="63" start="1260" width="20" count="1" />
        <bin index="75" start="1500" width="20" count="43" />
      </packetSizeHistogram>
      <flowInterruptionsHistogram nBins="0" >
      </flowInterruptionsHistogram>
    </Flow>
    <Flow flowId="22" timeFirstTxPacket="+28329157.0ns" timeFirstRxPacket="+28548821.0ns" timeLastTxPacket="+31498618.0ns" timeLastRxPacket="+31635760.0ns" delaySum="+12130219.0ns" jitterSum="+376236.0ns" lastDelay="+137142.0ns" txBytes="65888" rxBytes="65888" txPackets="47" rxPackets="47" lostPackets="0" timesForwarded="94">
      <delayHistogram nBins="1" >
        <bin index="0" start="0" width="0.001" count="47" />
      </delayHistogram>
      <jitterHistogram nBins="1" >
        <bin index="0" start="0" width="0.001" count="46" />
      </jitterHistogram>
      <packetSizeHistogram nBins="76" >
        <bin index="2" start="40" width="20" count="3" />
        <bin index="63" start="1260" width="20" count="1" />
        <bin index="75" start="1500" width="20" count="43" />
      </packetSizeHistogram>
      <flowInterruptionsHistogram nBins="0" >
      </flowInterruptionsHistogram>
    </Flow>
    <Flow flowId="23" timeFirstTxPacket="+28329157.0ns" timeFirstRxPacket="+28548860.0ns" timeLastTxPacket="+31504431.0ns" timeLastRxPacket="+31635793.0ns" delaySum="+12142650.0ns" jitterSum="+379191.0ns" lastDelay="+131362.0ns" txBytes="65888" rxBytes="65888" txPackets="47" rxPackets="47" lostPackets="0" timesForwarded="94">
      <delayHistogram nBins="1" >
        <bin index="0" start="0" width="0.001" count="47" />
      </delayHistogram>
      <jitterHistogram nBins="1" >
        <bin index="0" start="0" width="0.001" count="46" />
      </jitterHistogram>
      <packetSizeHistogram nBins="76" >
        <bin index="2" start="40" width="20" count="3" />
        <bin index="63" start="1260" width="20" count="1" />
        <bin index="75" start="1500" width="20" count="43" />
      </packetSizeHistogram>
      <flowInterruptionsHistogram nBins="0" >
      </flowInterruptionsHistogram>
    </Flow>
    <Flow flowId="24" timeFirstTxPacket="+28329157.0ns" timeFirstRxPacket="+28548899.0ns" timeLastTxPacket="+31510244.0ns" timeLastRxPacket="+31635826.0ns" delaySum="+12155081.0ns" jitterSum="+382146.0ns" lastDelay="+125582.0ns" txBytes="65888" rxBytes="65888" txPackets="47" rxPackets="47" lostPackets="0" timesForwarded="94">
      <delayHistogram nBins="1" >
        <bin index="0" start="0" width="0.001" count="47" />
      </delayHistogram>
      <jitterHistogram nBins="1" >
        <bin index="0" start="0" width="0.001" count="46" />
      </jitterHistogram>
      <packetSizeHistogram nBins="76" >
        <bin index="2" start="40" width="20" count="3" />
        <bin index="63" start="1260" width="20" count="1" />
        <bin index="75" start="1500" width="20" count="43" />
      </packetSizeHistogram>
      <flowInterruptionsHistogram nBins="0" >
      </flowInterruptionsHistogram>
    </Flow>
    <Flow flowId="25" timeFirstTxPacket="+28329157.0ns" timeFirstRxPacket="+28548938.0ns" timeLastTxPacket="+31516057.0ns" timeLastRxPacket="+31635859.0ns" delaySum="+12167512.0ns" jitterSum="+385101.0ns" lastDelay="+119802.0ns" txBytes="65888" rxBytes="65888" txPackets="47" rxPackets="47" lostPackets="0" timesForwarded="94">
      <delayHistogram nBins="1" >
        <bin index="0" start="0" width="0.001" count="47" />
      </delayHistogram>
      <jitterHistogram nBins="1" >
        <bin index="0" start="0" width="0.001" count="46" />
      </jitterHistogram>
      <packetSizeHistogram nBins="76" >
        <bin index="2" start="40" width="20" count="3" />
        <bin index="63" start="1260" width="20" count="1" />
        <bin index="75" start="1500" width="20" count="43" />
      </packetSizeHistogram>
      <flowInterruptionsHistogram nBins="0" >
      </flowInterruptionsHistogram>
    </Flow>
    <Flow flowId="26" timeFirstTxPacket="+28329157.0ns" timeFirstRxPacket="+28548977.0ns" timeLastTxPacket="+31521870.0ns" timeLastRxPacket="+31635892.0ns" delaySum="+12179943.0ns" jitterSum="+390458.0ns" lastDelay="+114022.0ns" txBytes="65888" rxBytes="65888" txPackets="47" rxPackets="47" lostPackets="0" timesForwarded="94">
      <delayHistogram nBins="1" >
        <bin index="0" start="0" width="0.001" count="47" />
      </delayHistogram>
      <jitterHistogram nBins="1" >
        <bin index="0" start="0" width="0.001" count="46" />
      </jitterHistogram>
      <packetSizeHistogram nBins="76" >
        <bin index="2" start="40" width="20" count="3" />
        <bin index="63" start="1260" width="20" count="1" />
        <bin index="75" start="1500" width="20" count="43" />
      </packetSizeHistogram>
      <flowInterruptionsHistogram nBins="0" >
      </flowInterruptionsHistogram>
    </Flow>
    <Flow flowId="27" timeFirstTxPacket="+28329157.0ns" timeFirstRxPacket="+28549016.0ns" timeLastTxPacket="+31527683.0ns" timeLastRxPacket="+31635925.0ns" delaySum="+12192374.0ns" jitterSum="+395815.0ns" lastDelay="+108242.0ns" txBytes="65888" rxBytes="65888" txPackets="47" rxPackets="47" lostPackets="0" timesForwarded="94">
      <delayHistogram nBins="1" >
        <bin index="0" start="0" width="0.001" count="47" />
      </delayHistogram>
      <jitterHistogram nBins="1" >
        <bin index="0" start="0" width="0.001" count="46" />
      </jitterHistogram>
      <packetSizeHistogram nBins="76" >
        <bin index="2" start="40" width="20" count="3" />
        <bin index="63" start="1260" width="20" count="1" />
        <bin index="75" start="1500" width="20" count="43" />
      </packetSizeHistogram>
      <flowInterruptionsHistogram nBins="0" >
      </flowInterruptionsHistogram>
    </Flow>
    <Flow flowId="28" timeFirstTxPacket="+28329157.0ns" timeFirstRxPacket="+28549055.0ns" timeLastTxPacket="+31533496.0ns" timeLastRxPacket="+31635958.0ns" delaySum="+12204805.0ns" jitterSum="+401172.0ns" lastDelay="+102462.0ns" txBytes="65888" rxBytes="65888" txPackets="47" rxPackets="47" lostPackets="0" timesForwarded="94">
      <delayHistogram nBins="1" >
        <bin index="0" start="0" width="0.001" count="47" />
      </delayHistogram>
      <jitterHistogram nBins="1" >
        <bin index="0" start="0" width="0.001" count="46" />
      </jitterHistogram>
      <packetSizeHistogram nBins="76" >
        <bin index="2" start="40" width="20" count="3" />
        <bin index="63" start="1260" width="20" count="1" />
        <bin index="75" start="1500" width="20" count="43" />
      </packetSizeHistogram>
      <flowInterruptionsHistogram nBins="0" >
      </flowInterruptionsHistogram>
    </Flow>
    <Flow flowId="29" timeFirstTxPacket="+28329157.0ns" timeFirstRxPacket="+28549094.0ns" timeLastTxPacket="+31539309.0ns" timeLastRxPacket="+31635991.0ns" delaySum="+12217236.0ns" jitterSum="+408931.0ns" lastDelay="+96682.0ns" txBytes="65888" rxBytes="65888" txPackets="47" rxPackets="47" lostPackets="0" timesForwarded="94">
      <delayHistogram nBins="1" >
        <bin index="0" start="0" width="0.001" count="47" />
      </delayHistogram>
      <jitterHistogram nBins="1" >
        <bin index="0" start="0" width="0.001" count="46" />
      </jitterHistogram>
      <packetSizeHistogram nBins="76" >
        <bin index="2" start="40" width="20" count="3" />
        <bin index="63" start="1260" width="20" count="1" />
        <bin index="75" start="1500" width="20" count="43" />
      </packetSizeHistogram>
      <flowInterruptionsHistogram nBins="0" >
      </flowInterruptionsHistogram>
    </Flow>
    <Flow flowId="30" timeFirstTxPacket="+28329157.0ns" timeFirstRxPacket="+28549133.0ns" timeLastTxPacket="+31545122.0ns" timeLastRxPacket="+31636024.0ns" delaySum="+12229667.0ns" jitterSum="+416690.0ns" lastDelay="+90902.0ns" txBytes="65888" rxBytes="65888" txPackets="47" rxPackets="47" lostPackets="0" timesForwarded="94">
      <delayHistogram nBins="1" >
        <bin index="0" start="0" width="0.001" count="47" />
      </delayHistogram>
      <jitterHistogram nBins="1" >
        <bin index="0" start="0" width="0.001" count="46" />
      </jitterHistogram>
      <packetSizeHistogram nBins="76" >
        <bin index="2" start="40" width="20" count="3" />
        <bin index="63" start="1260" width="20" count="1" />
        <bin index="75" start="1500" width="20" count="43" />
      </packetSizeHistogram>
      <flowInterruptionsHistogram nBins="0" >
      </flowInterruptionsHistogram>
    </Flow>
    <Flow flowId="31" timeFirstTxPacket="+28329157.0ns" timeFirstRxPacket="+28549172.0ns" timeLastTxPacket="+31550935.0ns" timeLastRxPacket="+31637258.0ns" delaySum="+12244500.0ns" jitterSum="+425650.0ns" lastDelay="+86323.0ns" txBytes="65888" rxBytes="65888" txPackets="47" rxPackets="47" lostPackets="0" timesForwarded="94">
      <delayHistogram nBins="1" >
        <bin index="0" start="0" width="0.001" count="47" />
      </delayHistogram>
      <jitterHistogram nBins="1" >
        <bin index="0" start="0" width="0.001" count="46" />
      </jitterHistogram>
      <packetSizeHistogram nBins="76" >
        <bin index="2" start="40" width="20" count="3" />
        <bin index="63" start="1260" width="20" count="1" />
        <bin index="75" start="1500" width="20" count="43" />
      </packetSizeHistogram>
      <flowInterruptionsHistogram nBins="0" >
      </flowInterruptionsHistogram>
    </Flow>
    <Flow flowId="32" timeFirstTxPacket="+28548236.0ns" timeFirstRxPacket="+28578353.0ns" timeLastTxPacket="+31529018.0ns" timeLastRxPacket="+31559150.0ns" delaySum="+1384605.0ns" jitterSum="+51.0ns" lastDelay="+30132.0ns" txBytes="1848" rxBytes="1848" txPackets="46" rxPackets="46" lostPackets="0" timesForwarded="92">
      <delayHistogram nBins="1" >
        <bin index="0" start="0" width="0.001" count="46" />
      </delayHistogram>
      <jitterHistogram nBins="1" >
        <bin index="0" start="0" width="0.001" count="45" />
      </jitterHistogram>
      <packetSizeHistogram nBins="3" >
        <bin index="2" start="40" width="20" count="46" />
      </packetSizeHistogram>
      <flowInterruptionsHistogram nBins="0" >
      </flowInterruptionsHistogram>
    </Flow>
    <Flow flowId="33" timeFirstTxPacket="+28548275.0ns" timeFirstRxPacket="+28578392.0ns" timeLastTxPacket="+31534831.0ns" timeLastRxPacket="+31564963.0ns" delaySum="+1384605.0ns" jitterSum="+51.0ns" lastDelay="+30132.0ns" txBytes="1848" rxBytes="1848" txPackets="46" rxPackets="46" lostPackets="0" timesForwarded="92">
      <delayHistogram nBins="1" >
        <bin index="0" start="0" width="0.001" count="46" />
      </delayHistogram>
      <jitterHistogram nBins="1" >
        <bin index="0" start="0" width="0.001" count="45" />
      </jitterHistogram>
      <packetSizeHistogram nBins="3" >
        <bin index="2" start="40" width="20" count="46" />
      </packetSizeHistogram>
      <flowInterruptionsHistogram nBins="0" >
      </flowInterruptionsHistogram>
    </Flow>
    <Flow flowId="34" timeFirstTxPacket="+28548314.0ns" timeFirstRxPacket="+28578431.0ns" timeLastTxPacket="+31540644.0ns" timeLastRxPacket="+31570776.0ns" delaySum="+1384605.0ns" jitterSum="+51.0ns" lastDelay="+30132.0ns" txBytes="1848" rxBytes="1848" txPackets="46" rxPackets="46" lostPackets="0" timesForwarded="92">
      <delayHistogram nBins="1" >
        <bin index="0" start="0" width="0.001" count="46" />
      </delayHistogram>
      <jitterHistogram nBins="1" >
        <bin index="0" start="0" width="0.001" count="45" />
      </jitterHistogram>
      <packetSizeHistogram nBins="3" >
        <bin index="2" start="40" width="20" count="46" />
      </packetSizeHistogram>
      <flowInterruptionsHistogram nBins="0" >
      </flowInterruptionsHistogram>
    </Flow>
    <Flow flowId="35" timeFirstTxPacket="+28548353.0ns" timeFirstRxPacket="+28578470.0ns" timeLastTxPacket="+31545256.0ns" timeLastRxPacket="+31575388.0ns" delaySum="+1384605.0ns" jitterSum="+51.0ns" lastDelay="+30132.0ns" txBytes="1848" rxBytes="1848" txPackets="46" rxPackets="46" lostPackets="0" timesForwarded="92">
      <delayHistogram nBins="1" >
        <bin index="0" start="0" width="0.001" count="46" />
      </delayHistogram>
      <jitterHistogram nBins="1" >
        <bin index="0" start="0" width="0.001" count="45" />
      </jitterHistogram>
      <packetSizeHistogram nBins="3" >
        <bin index="2" start="40" width="20" count="46" />
      </packetSizeHistogram>
      <flowInterruptionsHistogram nBins="0" >
      </flowInterruptionsHistogram>
    </Flow>
    <Flow flowId="36" timeFirstTxPacket="+28548392.0ns" timeFirstRxPacket="+28578509.0ns" timeLastTxPacket="+31404543.0ns" timeLastRxPacket="+31434675.0ns" delaySum="+1384605.0ns" jitterSum="+51.0ns" lastDelay="+30132.0ns" txBytes="1848" rxBytes="1848" txPackets="46" rxPackets="46" lostPackets="0" timesForwarded="92">
      <delayHistogram nBins="1" >
        <bin index="0" start="0" width="0.001" count="46" />
      </delayHistogram>
      <jitterHistogram nBins="1" >
        <bin index="0" start="0" width="0.001" count="45" />
      </jitterHistogram>
      <packetSizeHistogram nBins="3" >
        <bin index="2" start="40" width="20" count="46" />
      </packetSizeHistogram>
      <flowInterruptionsHistogram nBins="0" >
      </flowInterruptionsHistogram>
    </Flow>
    <Flow flowId="37" timeFirstTxPacket="+28548431.0ns" timeFirstRxPacket="+28578548.0ns" timeLastTxPacket="+31410356.0ns" timeLastRxPacket="+31440488.0ns" delaySum="+1384605.0ns" jitterSum="+51.0ns" lastDelay="+30132.0ns" txBytes="1848" rxBytes="1848" txPackets="46" rxPackets="46" lostPackets="0" timesForwarded="92">
      <delayHistogram nBins="1" >
        <bin index="0" start="0" width="0.001" count="46" />
      </delayHistogram>
      <jitterHistogram nBins="1" >
        <bin index="0" start="0" width="0.001" count="45" />
      </jitterHistogram>
      <packetSizeHistogram nBins="3" >
        <bin index="2" start="40" width="20" count="46" />
      </packetSizeHistogram>
      <flowInterruptionsHistogram nBins="0" >
      </flowInterruptionsHistogram>
    </Flow>
    <Flow flowId="38" timeFirstTxPacket="+28548470.0ns" timeFirstRxPacket="+28578587.0ns" timeLastTxPacket="+31416169.0ns" timeLastRxPacket="+31446301.0ns" delaySum="+1384605.0ns" jitterSum="+51.0ns" lastDelay="+30132.0ns" txBytes="1848" rxBytes="1848" txPackets="46" rxPackets="46" lostPackets="0" timesForwarded="92">
      <delayHistogram nBins="1" >
        <bin index="0" start="0" width="0.001" count="46" />
      </delayHistogram>
      <jitterHistogram nBins="1" >
        <bin index="0" start="0" width="0.001" count="45" />
      </jitterHistogram>
      <packetSizeHistogram nBins="3" >
        <bin index="2" start="40" width="20" count="46" />
      </packetSizeHistogram>
      <flowInterruptionsHistogram nBins="0" >
      </flowInterruptionsHistogram>
    </Flow>
    <Flow flowId="39" timeFirstTxPacket="+28548509.0ns" timeFirstRxPacket="+28578626.0ns" timeLastTxPacket="+31421982.0ns" timeLastRxPacket="+31452114.0ns" delaySum="+1384605.0ns" jitterSum="+51.0ns" lastDelay="+30132.0ns" txBytes="1848" rxBytes="1848" txPackets="46" rxPackets="46" lostPackets="0" timesForwarded="92">
      <delayHistogram nBins="1" >
        <bin index="0" start="0" width="0.001" count="46" />
      </delayHistogram>
      <jitterHistogram nBins="1" >
        <bin index="0" start="0" width="0.001" count="45" />
      </jitterHistogram>
      <packetSizeHistogram nBins="3" >
        <bin index="2" start="40" width="20" count="46" />
      </packetSizeHistogram>
      <flowInterruptionsHistogram nBins="0" >
      </flowInterruptionsHistogram>
    </Flow>
    <Flow flowId="40" timeFirstTxPacket="+28548548.0ns" timeFirstRxPacket="+28578665.0ns" timeLastTxPacket="+31427795.0ns" timeLastRxPacket="+31457927.0ns" delaySum="+1384605.0ns" jitterSum="+51.0ns" lastDelay="+30132.0ns" txBytes="1848" rxBytes="1848" txPackets="46" rxPackets="46" lostPackets="0" timesForwarded="92">
      <delayHistogram nBins="1" >
        <bin index="0" start="0" width="0.001" count="46" />
      </delayHistogram>
      <jitterHistogram nBins="1" >
        <bin index="0" start="0" width="0.001" count="45" />
      </jitterHistogram>
      <packetSizeHistogram nBins="3" >
        <bin index="2" start="40" width="20" count="46" />
      </packetSizeHistogram>
      <flowInterruptionsHistogram nBins="0" >
      </flowInterruptionsHistogram>
    </Flow>
    <Flow flowId="41" timeFirstTxPacket="+28548587.0ns" timeFirstRxPacket="+28578704.0ns" timeLastTxPacket="+31433608.0ns" timeLastRxPacket="+31463740.0ns" delaySum="+1384605.0ns" jitterSum="+51.0ns" lastDelay="+30132.0ns" txBytes="1848" rxBytes="1848" txPackets="46" rxPackets="46" lostPackets="0" timesForwarded="92">
      <delayHistogram nBins="1" >
        <bin index="0" start="0" width="0.001" count="46" />
      </delayHistogram>
      <jitterHistogram nBins="1" >
        <bin index="0" start="0" width="0.001" count="45" />
      </jitterHistogram>
      <packetSizeHistogram nBins="3" >
        <bin index="2" start="40" width="20" count="46" />
      </packetSizeHistogram>
      <flowInterruptionsHistogram nBins="0" >
      </flowInterruptionsHistogram>
    </Flow>
    <Flow flowId="42" timeFirstTxPacket="+28548626.0ns" timeFirstRxPacket="+28578743.0ns" timeLastTxPacket="+31439421.0ns" timeLastRxPacket="+31469553.0ns" delaySum="+1384605.0ns" jitterSum="+51.0ns" lastDelay="+30132.0ns" txBytes="1848" rxBytes="1848" txPackets="46" rxPackets="46" lostPackets="0" timesForwarded="92">
      <delayHistogram nBins="1" >
        <bin index="0" start="0" width="0.001" count="46" />
      </delayHistogram>
      <jitterHistogram nBins="1" >
        <bin index="0" start="0" width="0.001" count="45" />
      </jitterHistogram>
      <packetSizeHistogram nBins="3" >
        <bin index="2" start="40" width="20" count="46" />
      </packetSizeHistogram>
      <flowInterruptionsHistogram nBins="0" >
      </flowInterruptionsHistogram>
    </Flow>
    <Flow flowId="43" timeFirstTxPacket="+28548665.0ns" timeFirstRxPacket="+28578782.0ns" timeLastTxPacket="+31445234.0ns" timeLastRxPacket="+31475366.0ns" delaySum="+1384605.0ns" jitterSum="+51.0ns" lastDelay="+30132.0ns" txBytes="1848" rxBytes="1848" txPackets="46" rxPackets="46" lostPackets="0" timesForwarded="92">
      <delayHistogram nBins="1" >
        <bin index="0" start="0" width="0.001" count="46" />
      </delayHistogram>
      <jitterHistogram nBins="1" >
        <bin index="0" start="0" width="0.001" count="45" />
      </jitterHistogram>
      <packetSizeHistogram nBins="3" >
        <bin index="2" start="40" width="20" count="46" />
      </packetSizeHistogram>
      <flowInterruptionsHistogram nBins="0" >
      </flowInterruptionsHistogram>
    </Flow>
    <Flow flowId="44" timeFirstTxPacket="+28548704.0ns" timeFirstRxPacket="+28578821.0ns" timeLastTxPacket="+31451047.0ns" timeLastRxPacket="+31481179.0ns" delaySum="+1384605.0ns" jitterSum="+51.0ns" lastDelay="+30132.0ns" txBytes="1848" rxBytes="1848" txPackets="46" rxPackets="46" lostPackets="0" timesForwarded="92">
      <delayHistogram nBins="1" >
        <bin index="0" start="0" width="0.001" count="46" />
      </delayHistogram>
      <jitterHistogram nBins="1" >
        <bin index="0" start="0" width="0.001" count="45" />
      </jitterHistogram>
      <packetSizeHistogram nBins="3" >
        <bin index="2" start="40" width="20" count="46" />
      </packetSizeHistogram>
      <flowInterruptionsHistogram nBins="0" >
      </flowInterruptionsHistogram>
    </Flow>
    <Flow flowId="45" timeFirstTxPacket="+28548743.0ns" timeFirstRxPacket="+28578860.0ns" timeLastTxPacket="+31456860.0ns" timeLastRxPacket="+31486992.0ns" delaySum="+1384605.0ns" jitterSum="+51.0ns" lastDelay="+30132.0ns" txBytes="1848" rxBytes="1848" txPackets="46" rxPackets="46" lostPackets="0" timesForwarded="92">
      <delayHistogram nBins="1" >
        <bin index="0" start="0" width="0.001" count="46" />
      </delayHistogram>
      <jitterHistogram nBins="1" >
        <bin index="0" start="0" width="0.001" count="45" />
      </jitterHistogram>
      <packetSizeHistogram nBins="3" >
        <bin index="2" start="40" width="20" count="46" />
      </packetSizeHistogram>
      <flowInterruptionsHistogram nBins="0" >
      </flowInterruptionsHistogram>
    </Flow>
    <Flow flowId="46" timeFirstTxPacket="+28548782.0ns" timeFirstRxPacket="+28578899.0ns" timeLastTxPacket="+31462673.0ns" timeLastRxPacket="+31492805.0ns" delaySum="+1384605.0ns" jitterSum="+51.0ns" lastDelay="+30132.0ns" txBytes="1848" rxBytes="1848" txPackets="46" rxPackets="46" lostPackets="0" timesForwarded="92">
      <delayHistogram nBins="1" >
        <bin index="0" start="0" width="0.001" count="46" />
      </delayHistogram>
      <jitterHistogram nBins="1" >
        <bin index="0" start="0" width="0.001" count="45" />
      </jitterHistogram>
      <packetSizeHistogram nBins="3" >
        <bin index="2" start="40" width="20" count="46" />
      </packetSizeHistogram>
      <flowInterruptionsHistogram nBins="0" >
      </flowInterruptionsHistogram>
    </Flow>
    <Flow flowId="47" timeFirstTxPacket="+28548821.0ns" timeFirstRxPacket="+28578938.0ns" timeLastTxPacket="+31468486.0ns" timeLastRxPacket="+31498618.0ns" delaySum="+1384605.0ns" jitterSum="+51.0ns" lastDelay="+30132.0ns" txBytes="1848" rxBytes="1848" txPackets="46" rxPackets="46" lostPackets="0" timesForwarded="92">
      <delayHistogram nBins="1" >
        <bin index="0" start="0" width="0.001" count="46" />
      </delayHistogram>
      <jitterHistogram nBins="1" >
        <bin index="0" start="0" width="0.001" count="45" />
      </jitterHistogram>
      <packetSizeHistogram nBins="3" >
        <bin index="2" start="40" width="20" count="46" />
      </packetSizeHistogram>
      <flowInterruptionsHistogram nBins="0" >
      </flowInterruptionsHistogram>
    </Flow>
    <Flow flowId="48" timeFirstTxPacket="+28548860.0ns" timeFirstRxPacket="+28578977.0ns" timeLastTxPacket="+31474299.0ns" timeLastRxPacket="+31504431.0ns" delaySum="+1384605.0ns" jitterSum="+51.0ns" lastDelay="+30132.0ns" txBytes="1848" rxBytes="1848" txPackets="46" rxPackets="46" lostPackets="0" timesForwarded="92">
      <delayHistogram nBins="1" >
        <bin index="0" start="0" width="0.001" count="46" />
      </delayHistogram>
      <jitterHistogram nBins="1" >
        <bin index="0" start="0" width="0.001" count="45" />
      </jitterHistogram>
      <packetSizeHistogram nBins="3" >
        <bin index="2" start="40" width="20" count="46" />
      </packetSizeHistogram>
      <flowInterruptionsHistogram nBins="0" >
      </flowInterruptionsHistogram>
    </Flow>
    <Flow flowId="49" timeFirstTxPacket="+28548899.0ns" timeFirstRxPacket="+28579016.0ns" timeLastTxPacket="+31480112.0ns" timeLastRxPacket="+31510244.0ns" delaySum="+1384605.0ns" jitterSum="+51.0ns" lastDelay="+30132.0ns" txBytes="1848" rxBytes="1848" txPackets="46" rxPackets="46" lostPackets="0" timesForwarded="92">
      <delayHistogram nBins="1" >
        <bin index="0" start="0" width="0.001" count="46" />
      </delayHistogram>
      <jitterHistogram nBins="1" >
        <bin index="0" start="0" width="0.001" count="45" />
      </jitterHistogram>
      <packetSizeHistogram nBins="3" >
        <bin index="2" start="40" width="20" count="46" />
      </packetSizeHistogram>
      <flowInterruptionsHistogram nBins="0" >
      </flowInterruptionsHistogram>
    </Flow>
    <Flow flowId="50" timeFirstTxPacket="+28548938.0ns" timeFirstRxPacket="+28579055.0ns" timeLastTxPacket="+31485925.0ns" timeLastRxPacket="+31516057.0ns" delaySum="+1384605.0ns" jitterSum="+51.0ns" lastDelay="+30132.0ns" txBytes="1848" rxBytes="1848" txPackets="46" rxPackets="46" lostPackets="0" timesForwarded="92">
      <delayHistogram nBins="1" >
        <bin index="0" start="0" width="0.001" count="46" />
      </delayHistogram>
      <jitterHistogram nBins="1" >
        <bin index="0" start="0" width="0.001" count="45" />
      </jitterHistogram>
      <packetSizeHistogram nBins="3" >
        <bin index="2" start="40" width="20" count="46" />
      </packetSizeHistogram>
      <flowInterruptionsHistogram nBins="0" >
      </flowInterruptionsHistogram>
    </Flow>
    <Flow flowId="51" timeFirstTxPacket="+28548977.0ns" timeFirstRxPacket="+28579094.0ns" timeLastTxPacket="+31491738.0ns" timeLastRxPacket="+31521870.0ns" delaySum="+1384605.0ns" jitterSum="+51.0ns" lastDelay="+30132.0ns" txBytes="1848" rxBytes="1848" txPackets="46" rxPackets="46" lostPackets="0" timesForwarded="92">
      <delayHistogram nBins="1" >
        <bin index="0" start="0" width="0.001" count="46" />
      </delayHistogram>
      <jitterHistogram nBins="1" >
        <bin index="0" start="0" width="0.001" count="45" />
      </jitterHistogram>
      <packetSizeHistogram nBins="3" >
        <bin index="2" start="40" width="20" count="46" />
      </packetSizeHistogram>
      <flowInterruptionsHistogram nBins="0" >
      </flowInterruptionsHistogram>
    </Flow>
    <Flow flowId="52" timeFirstTxPacket="+28549016.0ns" timeFirstRxPacket="+28579133.0ns" timeLastTxPacket="+31497551.0ns" timeLastRxPacket="+31527683.0ns" delaySum="+1384605.0ns" jitterSum="+51.0ns" lastDelay="+30132.0ns" txBytes="1848" rxBytes="1848" txPackets="46" rxPackets="46" lostPackets="0" timesForwarded="92">
      <delayHistogram nBins="1" >
        <bin index="0" start="0" width="0.001" count="46" />
      </delayHistogram>
      <jitterHistogram nBins="1" >
        <bin index="0" start="0" width="0.001" count="45" />
      </jitterHistogram>
      <packetSizeHistogram nBins="3" >
        <bin index="2" start="40" width="20" count="46" />
      </packetSizeHistogram>
      <flowInterruptionsHistogram nBins="0" >
      </flowInterruptionsHistogram>
    </Flow>
    <Flow flowId="53" timeFirstTxPacket="+28549055.0ns" timeFirstRxPacket="+28579172.0ns" timeLastTxPacket="+31503364.0ns" timeLastRxPacket="+31533496.0ns" delaySum="+1384605.0ns" jitterSum="+51.0ns" lastDelay="+30132.0ns" txBytes="1848" rxBytes="1848" txPackets="46" rxPackets="46" lostPackets="0" timesForwarded="92">
      <delayHistogram nBins="1" >
        <bin index="0" start="0" width="0.001" count="46" />
      </delayHistogram>
      <jitterHistogram nBins="1" >
        <bin index="0" start="0" width="0.001" count="45" />
      </jitterHistogram>
      <packetSizeHistogram nBins="3" >
        <bin index="2" start="40" width="20" count="46" />
      </packetSizeHistogram>
      <flowInterruptionsHistogram nBins="0" >
      </flowInterruptionsHistogram>
    </Flow>
    <Flow flowId="54" timeFirstTxPacket="+28549094.0ns" timeFirstRxPacket="+28579211.0ns" timeLastTxPacket="+31509177.0ns" timeLastRxPacket="+31539309.0ns" delaySum="+1384605.0ns" jitterSum="+51.0ns" lastDelay="+30132.0ns" txBytes="1848" rxBytes="1848" txPackets="46" rxPackets="46" lostPackets="0" timesForwarded="92">
      <delayHistogram nBins="1" >
        <bin index="0" start="0" width="0.001" count="46" />
      </delayHistogram>
      <jitterHistogram nBins="1" >
        <bin index="0" start="0" width="0.001" count="45" />
      </jitterHistogram>
      <packetSizeHistogram nBins="3" >
        <bin index="2" start="40" width="20" count="46" />
      </packetSizeHistogram>
      <flowInterruptionsHistogram nBins="0" >
      </flowInterruptionsHistogram>
    </Flow>
    <Flow flowId="55" timeFirstTxPacket="+28549133.0ns" timeFirstRxPacket="+28579250.0ns" timeLastTxPacket="+31514990.0ns" timeLastRxPacket="+31545122.0ns" delaySum="+1384605.0ns" jitterSum="+51.0ns" lastDelay="+30132.0ns" txBytes="1848" rxBytes="1848" txPackets="46" rxPackets="46" lostPackets="0" timesForwarded="92">
      <delayHistogram nBins="1" >
        <bin index="0" start="0" width="0.001" count="46" />
      </delayHistogram>
      <jitterHistogram nBins="1" >
        <bin index="0" start="0" width="0.001" count="45" />
      </jitterHistogram>
      <packetSizeHistogram nBins="3" >
        <bin index="2" start="40" width="20" count="46" />
      </packetSizeHistogram>
      <flowInterruptionsHistogram nBins="0" >
      </flowInterruptionsHistogram>
    </Flow>
    <Flow flowId="56" timeFirstTxPacket="+28549172.0ns" timeFirstRxPacket="+28579289.0ns" timeLastTxPacket="+31520803.0ns" timeLastRxPacket="+31550935.0ns" delaySum="+1384605.0ns" jitterSum="+51.0ns" lastDelay="+30132.0ns" txBytes="1848" rxBytes="1848" txPackets="46" rxPackets="46" lostPackets="0" timesForwarded="92">
      <delayHistogram nBins="1" >
        <bin index="0" start="0" width="0.001" count="46" />
      </delayHistogram>
      <jitterHistogram nBins="1" >
        <bin index="0" start="0" width="0.001" count="45" />
      </jitterHistogram>
      <packetSizeHistogram nBins="3" >
        <bin index="2" start="40" width="20" count="46" />
      </packetSizeHistogram>
      <flowInterruptionsHistogram nBins="0" >
      </flowInterruptionsHistogram>
    </Flow>
  </FlowStats>
  <Ipv4FlowClassifier>
    <Flow flowId="1" sourceAddress="10.0.1.1" destinationAddress="10.0.30.2" protocol="6" sourcePort="49153" destinationPort="50000">
      <Dscp value="0x0" packets="14064" />
    </Flow>
    <Flow flowId="2" sourceAddress="10.0.2.1" destinationAddress="10.0.30.2" protocol="6" sourcePort="49153" destinationPort="50000">
      <Dscp value="0x0" packets="13411" />
    </Flow>
    <Flow flowId="3" sourceAddress="10.0.3.1" destinationAddress="10.0.30.2" protocol="6" sourcePort="49153" destinationPort="50000">
      <Dscp value="0x0" packets="13053" />
    </Flow>
    <Flow flowId="7" sourceAddress="10.0.4.1" destinationAddress="10.0.31.2" protocol="6" sourcePort="49153" destinationPort="50000">
      <Dscp value="0x0" packets="47" />
    </Flow>
    <Flow flowId="8" sourceAddress="10.0.5.1" destinationAddress="10.0.31.2" protocol="6" sourcePort="49153" destinationPort="50000">
      <Dscp value="0x0" packets="47" />
    </Flow>
    <Flow flowId="9" sourceAddress="10.0.6.1" destinationAddress="10.0.31.2" protocol="6" sourcePort="49153" destinationPort="50000">
      <Dscp value="0x0" packets="47" />
    </Flow>
    <Flow flowId="10" sourceAddress="10.0.7.1" destinationAddress="10.0.31.2" protocol="6" sourcePort="49153" destinationPort="50000">
      <Dscp value="0x0" packets="47" />
    </Flow>
    <Flow flowId="11" sourceAddress="10.0.8.1" destinationAddress="10.0.31.2" protocol="6" sourcePort="49153" destinationPort="50000">
      <Dscp value="0x0" packets="47" />
    </Flow>
    <Flow flowId="12" sourceAddress="10.0.9.1" destinationAddress="10.0.31.2" protocol="6" sourcePort="49153" destinationPort="50000">
      <Dscp value="0x0" packets="47" />
    </Flow>
    <Flow flowId="13" sourceAddress="10.0.10.1" destinationAddress="10.0.31.2" protocol="6" sourcePort="49153" destinationPort="50000">
      <Dscp value="0x0" packets="47" />
    </Flow>
    <Flow flowId="14" sourceAddress="10.0.11.1" destinationAddress="10.0.31.2" protocol="6" sourcePort="49153" destinationPort="50000">
      <Dscp value="0x0" packets="47" />
    </Flow>
    <Flow flowId="15" sourceAddress="10.0.12.1" destinationAddress="10.0.31.2" protocol="6" sourcePort="49153" destinationPort="50000">
      <Dscp value="0x0" packets="47" />
    </Flow>
    <Flow flowId="16" sourceAddress="10.0.13.1" destinationAddress="10.0.31.2" protocol="6" sourcePort="49153" destinationPort="50000">
      <Dscp value="0x0" packets="47" />
    </Flow>
    <Flow flowId="17" sourceAddress="10.0.14.1" destinationAddress="10.0.31.2" protocol="6" sourcePort="49153" destinationPort="50000">
      <Dscp value="0x0" packets="47" />
    </Flow>
    <Flow flowId="18" sourceAddress="10.0.15.1" destinationAddress="10.0.31.2" protocol="6" sourcePort="49153" destinationPort="50000">
      <Dscp value="0x0" packets="47" />
    </Flow>
    <Flow flowId="19" sourceAddress="10.0.16.1" destinationAddress="10.0.31.2" protocol="6" sourcePort="49153" destinationPort="50000">
      <Dscp value="0x0" packets="47" />
    </Flow>
    <Flow flowId="20" sourceAddress="10.0.17.1" destinationAddress="10.0.31.2" protocol="6" sourcePort="49153" destinationPort="50000">
      <Dscp value="0x0" packets="47" />
    </Flow>
    <Flow flowId="21" sourceAddress="10.0.18.1" destinationAddress="10.0.31.2" protocol="6" sourcePort="49153" destinationPort="50000">
      <Dscp value="0x0" packets="47" />
    </Flow>
    <Flow flowId="22" sourceAddress="10.0.19.1" destinationAddress="10.0.31.2" protocol="6" sourcePort="49153" destinationPort="50000">
      <Dscp value="0x0" packets="47" />
    </Flow>
    <Flow flowId="23" sourceAddress="10.0.20.1" destinationAddress="10.0.31.2" protocol="6" sourcePort="49153" destinationPort="50000">
      <Dscp value="0x0" packets="47" />
    </Flow>
    <Flow flowId="24" sourceAddress="10.0.21.1" destinationAddress="10.0.31.2" protocol="6" sourcePort="49153" destinationPort="50000">
      <Dscp value="0x0" packets="47" />
    </Flow>
    <Flow flowId="25" sourceAddress="10.0.22.1" destinationAddress="10.0.31.2" protocol="6" sourcePort="49153" destinationPort="50000">
      <Dscp value="0x0" packets="47" />
    </Flow>
    <Flow flowId="26" sourceAddress="10.0.23.1" destinationAddress="10.0.31.2" protocol="6" sourcePort="49153" destinationPort="50000">
      <Dscp value="0x0" packets="47" />
    </Flow>
    <Flow flowId="27" sourceAddress="10.0.24.1" destinationAddress="10.0.31.2" protocol="6" sourcePort="49153" destinationPort="50000">
      <Dscp value="0x0" packets="47" />
    </Flow>
    <Flow flowId="28" sourceAddress="10.0.25.1" destinationAddress="10.0.31.2" protocol="6" sourcePort="49153" destinationPort="50000">
      <Dscp value="0x0" packets="47" />
    </Flow>
    <Flow flowId="29" sourceAddress="10.0.26.1" destinationAddress="10.0.31.2" protocol="6" sourcePort="49153" destinationPort="50000">
      <Dscp value="0x0" packets="47" />
    </Flow>
    <Flow flowId="30" sourceAddress="10.0.27.1" destinationAddress="10.0.31.2" protocol="6" sourcePort="49153" destinationPort="50000">
      <Dscp value="0x0" packets="47" />
    </Flow>
    <Flow flowId="31" sourceAddress="10.0.28.1" destinationAddress="10.0.31.2" protocol="6" sourcePort="49153" destinationPort="50000">
      <Dscp value="0x0" packets="47" />
    </Flow>
    <Flow flowId="4" sourceAddress="10.0.30.2" destinationAddress="10.0.1.1" protocol="6" sourcePort="50000" destinationPort="49153">
      <Dscp value="0x0" packets="13988" />
    </Flow>
    <Flow flowId="5" sourceAddress="10.0.30.2" destinationAddress="10.0.2.1" protocol="6" sourcePort="50000" destinationPort="49153">
      <Dscp value="0x0" packets="13361" />
    </Flow>
    <Flow flowId="6" sourceAddress="10.0.30.2" destinationAddress="10.0.3.1" protocol="6" sourcePort="50000" destinationPort="49153">
      <Dscp value="0x0" packets="12988" />
    </Flow>
    <Flow flowId="32" sourceAddress="10.0.31.2" destinationAddress="10.0.4.1" protocol="6" sourcePort="50000" destinationPort="49153">
      <Dscp value="0x0" packets="46" />
    </Flow>
    <Flow flowId="33" sourceAddress="10.0.31.2" destinationAddress="10.0.5.1" protocol="6" sourcePort="50000" destinationPort="49153">
      <Dscp value="0x0" packets="46" />
    </Flow>
    <Flow flowId="34" sourceAddress="10.0.31.2" destinationAddress="10.0.6.1" protocol="6" sourcePort="50000" destinationPort="49153">
      <Dscp value="0x0" packets="46" />
    </Flow>
    <Flow flowId="35" sourceAddress="10.0.31.2" destinationAddress="10.0.7.1" protocol="6" sourcePort="50000" destinationPort="49153">
      <Dscp value="0x0" packets="46" />
    </Flow>
    <Flow flowId="36" sourceAddress="10.0.31.2" destinationAddress="10.0.8.1" protocol="6" sourcePort="50000" destinationPort="49153">
      <Dscp value="0x0" packets="46" />
    </Flow>
    <Flow flowId="37" sourceAddress="10.0.31.2" destinationAddress="10.0.9.1" protocol="6" sourcePort="50000" destinationPort="49153">
      <Dscp value="0x0" packets="46" />
    </Flow>
    <Flow flowId="38" sourceAddress="10.0.31.2" destinationAddress="10.0.10.1" protocol="6" sourcePort="50000" destinationPort="49153">
      <Dscp value="0x0" packets="46" />
    </Flow>
    <Flow flowId="39" sourceAddress="10.0.31.2" destinationAddress="10.0.11.1" protocol="6" sourcePort="50000" destinationPort="49153">
      <Dscp value="0x0" packets="46" />
    </Flow>
    <Flow flowId="40" sourceAddress="10.0.31.2" destinationAddress="10.0.12.1" protocol="6" sourcePort="50000" destinationPort="49153">
      <Dscp value="0x0" packets="46" />
    </Flow>
    <Flow flowId="41" sourceAddress="10.0.31.2" destinationAddress="10.0.13.1" protocol="6" sourcePort="50000" destinationPort="49153">
      <Dscp value="0x0" packets="46" />
    </Flow>
    <Flow flowId="42" sourceAddress="10.0.31.2" destinationAddress="10.0.14.1" protocol="6" sourcePort="50000" destinationPort="49153">
      <Dscp value="0x0" packets="46" />
    </Flow>
    <Flow flowId="43" sourceAddress="10.0.31.2" destinationAddress="10.0.15.1" protocol="6" sourcePort="50000" destinationPort="49153">
      <Dscp value="0x0" packets="46" />
    </Flow>
    <Flow flowId="44" sourceAddress="10.0.31.2" destinationAddress="10.0.16.1" protocol="6" sourcePort="50000" destinationPort="49153">
      <Dscp value="0x0" packets="46" />
    </Flow>
    <Flow flowId="45" sourceAddress="10.0.31.2" destinationAddress="10.0.17.1" protocol="6" sourcePort="50000" destinationPort="49153">
      <Dscp value="0x0" packets="46" />
    </Flow>
    <Flow flowId="46" sourceAddress="10.0.31.2" destinationAddress="10.0.18.1" protocol="6" sourcePort="50000" destinationPort="49153">
      <Dscp value="0x0" packets="46" />
    </Flow>
    <Flow flowId="47" sourceAddress="10.0.31.2" destinationAddress="10.0.19.1" protocol="6" sourcePort="50000" destinationPort="49153">
      <Dscp value="0x0" packets="46" />
    </Flow>
    <Flow flowId="48" sourceAddress="10.0.31.2" destinationAddress="10.0.20.1" protocol="6" sourcePort="50000" destinationPort="49153">
      <Dscp value="0x0" packets="46" />
    </Flow>
    <Flow flowId="49" sourceAddress="10.0.31.2" destinationAddress="10.0.21.1" protocol="6" sourcePort="50000" destinationPort="49153">
      <Dscp value="0x0" packets="46" />
    </Flow>
    <Flow flowId="50" sourceAddress="10.0.31.2" destinationAddress="10.0.22.1" protocol="6" sourcePort="50000" destinationPort="49153">
      <Dscp value="0x0" packets="46" />
    </Flow>
    <Flow flowId="51" sourceAddress="10.0.31.2" destinationAddress="10.0.23.1" protocol="6" sourcePort="50000" destinationPort="49153">
      <Dscp value="0x0" packets="46" />
    </Flow>
    <Flow flowId="52" sourceAddress="10.0.31.2" destinationAddress="10.0.24.1" protocol="6" sourcePort="50000" destinationPort="49153">
      <Dscp value="0x0" packets="46" />
    </Flow>
    <Flow flowId="53" sourceAddress="10.0.31.2" destinationAddress="10.0.25.1" protocol="6" sourcePort="50000" destinationPort="49153">
      <Dscp value="0x0" packets="46" />
    </Flow>
    <Flow flowId="54" sourceAddress="10.0.31.2" destinationAddress="10.0.26.1" protocol="6" sourcePort="50000" destinationPort="49153">
      <Dscp value="0x0" packets="46" />
    </Flow>
    <Flow flowId="55" sourceAddress="10.0.31.2" destinationAddress="10.0.27.1" protocol="6" sourcePort="50000" destinationPort="49153">
      <Dscp value="0x0" packets="46" />
    </Flow>
    <Flow flowId="56" sourceAddress="10.0.31.2" destinationAddress="10.0.28.1" protocol="6" sourcePort="50000" destinationPort="49153">
      <Dscp value="0x0" packets="46" />
    </Flow>
  </Ipv4FlowClassifier>
  <Ipv6FlowClassifier>
  </Ipv6FlowClassifier>
  <FlowProbes>
    <FlowProbe index="0">
      <FlowStats  flowId="1" packets="14064" bytes="21093088" delayFromFirstProbeSum="+158628714.0ns" >
      </FlowStats>
      <FlowStats  flowId="2" packets="13402" bytes="20100088" delayFromFirstProbeSum="+150754210.0ns" >
      </FlowStats>
      <FlowStats  flowId="3" packets="13053" bytes="19576588" delayFromFirstProbeSum="+147622768.0ns" >
      </FlowStats>
      <FlowStats  flowId="4" packets="13988" bytes="559528" delayFromFirstProbeSum="+280683220.0ns" >
      </FlowStats>
      <FlowStats  flowId="5" packets="13348" bytes="533928" delayFromFirstProbeSum="+267840980.0ns" >
      </FlowStats>
      <FlowStats  flowId="6" packets="12984" bytes="519368" delayFromFirstProbeSum="+260536956.0ns" >
      </FlowStats>
      <FlowStats  flowId="7" packets="47" bytes="65888" delayFromFirstProbeSum="+532429.0ns" >
      </FlowStats>
      <FlowStats  flowId="8" packets="47" bytes="65888" delayFromFirstProbeSum="+532429.0ns" >
      </FlowStats>
      <FlowStats  flowId="9" packets="47" bytes="65888" delayFromFirstProbeSum="+532429.0ns" >
      </FlowStats>
      <FlowStats  flowId="10" packets="47" bytes="65888" delayFromFirstProbeSum="+532429.0ns" >
      </FlowStats>
      <FlowStats  flowId="11" packets="47" bytes="65888" delayFromFirstProbeSum="+531228.0ns" >
      </FlowStats>
      <FlowStats  flowId="12" packets="47" bytes="65888" delayFromFirstProbeSum="+531228.0ns" >
      </FlowStats>
      <FlowStats  flowId="13" packets="47" bytes="65888" delayFromFirstProbeSum="+531228.0ns" >
      </FlowStats>
      <FlowStats  flowId="14" packets="47" bytes="65888" delayFromFirstProbeSum="+531228.0ns" >
      </FlowStats>
      <FlowStats  flowId="15" packets="47" bytes="65888" delayFromFirstProbeSum="+531228.0ns" >
      </FlowStats>
      <FlowStats  flowId="16" packets="47" bytes="65888" delayFromFirstProbeSum="+531228.0ns" >
      </FlowStats>
      <FlowStats  flowId="17" packets="47" bytes="65888" delayFromFirstProbeSum="+531228.0ns" >
      </FlowStats>
      <FlowStats  flowId="18" packets="47" bytes="65888" delayFromFirstProbeSum="+531228.0ns" >
      </FlowStats>
      <FlowStats  flowId="19" packets="47" bytes="65888" delayFromFirstProbeSum="+531228.0ns" >
      </FlowStats>
      <FlowStats  flowId="20" packets="47" bytes="65888" delayFromFirstProbeSum="+531228.0ns" >
      </FlowStats>
      <FlowStats  flowId="21" packets="47" bytes="65888" delayFromFirstProbeSum="+531228.0ns" >
      </FlowStats>
      <FlowStats  flowId="22" packets="47" bytes="65888" delayFromFirstProbeSum="+531228.0ns" >
      </FlowStats>
      <FlowStats  flowId="23" packets="47" bytes="65888" delayFromFirstProbeSum="+531228.0ns" >
      </FlowStats>
      <FlowStats  flowId="24" packets="47" bytes="65888" delayFromFirstProbeSum="+531228.0ns" >
      </FlowStats>
      <FlowStats  flowId="25" packets="47" bytes="65888" delayFromFirstProbeSum="+531228.0ns" >
      </FlowStats>
      <FlowStats  flowId="26" packets="47" bytes="65888" delayFromFirstProbeSum="+531228.0ns" >
      </FlowStats>
      <FlowStats  flowId="27" packets="47" bytes="65888" delayFromFirstProbeSum="+531228.0ns" >
      </FlowStats>
      <FlowStats  flowId="28" packets="47" bytes="65888" delayFromFirstProbeSum="+531228.0ns" >
      </FlowStats>
      <FlowStats  flowId="29" packets="47" bytes="65888" delayFromFirstProbeSum="+531228.0ns" >
      </FlowStats>
      <FlowStats  flowId="30" packets="47" bytes="65888" delayFromFirstProbeSum="+531228.0ns" >
      </FlowStats>
      <FlowStats  flowId="31" packets="47" bytes="65888" delayFromFirstProbeSum="+530027.0ns" >
      </FlowStats>
      <FlowStats  flowId="32" packets="46" bytes="1848" delayFromFirstProbeSum="+923081.0ns" >
      </FlowStats>
      <FlowStats  flowId="33" packets="46" bytes="1848" delayFromFirstProbeSum="+923081.0ns" >
      </FlowStats>
      <FlowStats  flowId="34" packets="46" bytes="1848" delayFromFirstProbeSum="+923081.0ns" >
      </FlowStats>
      <FlowStats  flowId="35" packets="46" bytes="1848" delayFromFirstProbeSum="+923081.0ns" >
      </FlowStats>
      <FlowStats  flowId="36" packets="46" bytes="1848" delayFromFirstProbeSum="+923081.0ns" >
      </FlowStats>
      <FlowStats  flowId="37" packets="46" bytes="1848" delayFromFirstProbeSum="+923081.0ns" >
      </FlowStats>
      <FlowStats  flowId="38" packets="46" bytes="1848" delayFromFirstProbeSum="+923081.0ns" >
      </FlowStats>
      <FlowStats  flowId="39" packets="46" bytes="1848" delayFromFirstProbeSum="+923081.0ns" >
      </FlowStats>
      <FlowStats  flowId="40" packets="46" bytes="1848" delayFromFirstProbeSum="+923081.0ns" >
      </FlowStats>
      <FlowStats  flowId="41" packets="46" bytes="1848" delayFromFirstProbeSum="+923081.0ns" >
      </FlowStats>
      <FlowStats  flowId="42" packets="46" bytes="1848" delayFromFirstProbeSum="+923081.0ns" >
      </FlowStats>
      <FlowStats  flowId="43" packets="46" bytes="1848" delayFromFirstProbeSum="+923081.0ns" >
      </FlowStats>
      <FlowStats  flowId="44" packets="46" bytes="1848" delayFromFirstProbeSum="+923081.0ns" >
      </FlowStats>
      <FlowStats  flowId="45" packets="46" bytes="1848" delayFromFirstProbeSum="+923081.0ns" >
      </FlowStats>
      <FlowStats  flowId="46" packets="46" bytes="1848" delayFromFirstProbeSum="+923081.0ns" >
      </FlowStats>
      <FlowStats  flowId="47" packets="46" bytes="1848" delayFromFirstProbeSum="+923081.0ns" >
      </FlowStats>
      <FlowStats  flowId="48" packets="46" bytes="1848" delayFromFirstProbeSum="+923081.0ns" >
      </FlowStats>
      <FlowStats  flowId="49" packets="46" bytes="1848" delayFromFirstProbeSum="+923081.0ns" >
      </FlowStats>
      <FlowStats  flowId="50" packets="46" bytes="1848" delayFromFirstProbeSum="+923081.0ns" >
      </FlowStats>
      <FlowStats  flowId="51" packets="46" bytes="1848" delayFromFirstProbeSum="+923081.0ns" >
      </FlowStats>
      <FlowStats  flowId="52" packets="46" bytes="1848" delayFromFirstProbeSum="+923081.0ns" >
      </FlowStats>
      <FlowStats  flowId="53" packets="46" bytes="1848" delayFromFirstProbeSum="+923081.0ns" >
      </FlowStats>
      <FlowStats  flowId="54" packets="46" bytes="1848" delayFromFirstProbeSum="+923081.0ns" >
      </FlowStats>
      <FlowStats  flowId="55" packets="46" bytes="1848" delayFromFirstProbeSum="+923081.0ns" >
      </FlowStats>
      <FlowStats  flowId="56" packets="46" bytes="1848" delayFromFirstProbeSum="+923081.0ns" >
      </FlowStats>
    </FlowProbe>
    <FlowProbe index="1">
    </FlowProbe>
    <FlowProbe index="2">
      <FlowStats  flowId="1" packets="13989" bytes="20980588" delayFromFirstProbeSum="+2832320123.0ns" >
      </FlowStats>
      <FlowStats  flowId="2" packets="13365" bytes="20044588" delayFromFirstProbeSum="+2726143444.0ns" >
      </FlowStats>
      <FlowStats  flowId="3" packets="12995" bytes="19489588" delayFromFirstProbeSum="+2624327944.0ns" >
      </FlowStats>
      <FlowStats  flowId="4" packets="13988" bytes="559528" delayFromFirstProbeSum="+140341610.0ns" >
      </FlowStats>
      <FlowStats  flowId="5" packets="13356" bytes="534248" delayFromFirstProbeSum="+134000754.0ns" >
      </FlowStats>
      <FlowStats  flowId="6" packets="12985" bytes="519408" delayFromFirstProbeSum="+130278511.0ns" >
      </FlowStats>
      <FlowStats  flowId="7" packets="47" bytes="65888" delayFromFirstProbeSum="+11296550.0ns" >
      </FlowStats>
      <FlowStats  flowId="8" packets="47" bytes="65888" delayFromFirstProbeSum="+11304369.0ns" >
      </FlowStats>
      <FlowStats  flowId="9" packets="47" bytes="65888" delayFromFirstProbeSum="+11313197.0ns" >
      </FlowStats>
      <FlowStats  flowId="10" packets="47" bytes="65888" delayFromFirstProbeSum="+11322025.0ns" >
      </FlowStats>
      <FlowStats  flowId="11" packets="47" bytes="65888" delayFromFirstProbeSum="+11460729.0ns" >
      </FlowStats>
      <FlowStats  flowId="12" packets="47" bytes="65888" delayFromFirstProbeSum="+11475754.0ns" >
      </FlowStats>
      <FlowStats  flowId="13" packets="47" bytes="65888" delayFromFirstProbeSum="+11491788.0ns" >
      </FlowStats>
      <FlowStats  flowId="14" packets="47" bytes="65888" delayFromFirstProbeSum="+11505420.0ns" >
      </FlowStats>
      <FlowStats  flowId="15" packets="47" bytes="65888" delayFromFirstProbeSum="+11519052.0ns" >
      </FlowStats>
      <FlowStats  flowId="16" packets="47" bytes="65888" delayFromFirstProbeSum="+11532684.0ns" >
      </FlowStats>
      <FlowStats  flowId="17" packets="47" bytes="65888" delayFromFirstProbeSum="+11545115.0ns" >
      </FlowStats>
      <FlowStats  flowId="18" packets="47" bytes="65888" delayFromFirstProbeSum="+11557546.0ns" >
      </FlowStats>
      <FlowStats  flowId="19" packets="47" bytes="65888" delayFromFirstProbeSum="+11569977.0ns" >
      </FlowStats>
      <FlowStats  flowId="20" packets="47" bytes="65888" delayFromFirstProbeSum="+11582408.0ns" >
      </FlowStats>
      <FlowStats  flowId="21" packets="47" bytes="65888" delayFromFirstProbeSum="+11594839.0ns" >
      </FlowStats>
      <FlowStats  flowId="22" packets="47" bytes="65888" delayFromFirstProbeSum="+11607270.0ns" >
      </FlowStats>
      <FlowStats  flowId="23" packets="47" bytes="65888" delayFromFirstProbeSum="+11619701.0ns" >
      </FlowStats>
      <FlowStats  flowId="24" packets="47" bytes="65888" delayFromFirstProbeSum="+11632132.0ns" >
      </FlowStats>
      <FlowStats  flowId="25" packets="47" bytes="65888" delayFromFirstProbeSum="+11644563.0ns" >
      </FlowStats>
      <FlowStats  flowId="26" packets="47" bytes="65888" delayFromFirstProbeSum="+11656994.0ns" >
      </FlowStats>
      <FlowStats  flowId="27" packets="47" bytes="65888" delayFromFirstProbeSum="+11669425.0ns" >
      </FlowStats>
      <FlowStats  flowId="28" packets="47" bytes="65888" delayFromFirstProbeSum="+11681856.0ns" >
      </FlowStats>
      <FlowStats  flowId="29" packets="47" bytes="65888" delayFromFirstProbeSum="+11694287.0ns" >
      </FlowStats>
      <FlowStats  flowId="30" packets="47" bytes="65888" delayFromFirstProbeSum="+11706718.0ns" >
      </FlowStats>
      <FlowStats  flowId="31" packets="47" bytes="65888" delayFromFirstProbeSum="+11721551.0ns" >
      </FlowStats>
      <FlowStats  flowId="32" packets="46" bytes="1848" delayFromFirstProbeSum="+461557.0ns" >
      </FlowStats>
      <FlowStats  flowId="33" packets="46" bytes="1848" delayFromFirstProbeSum="+461557.0ns" >
      </FlowStats>
      <FlowStats  flowId="34" packets="46" bytes="1848" delayFromFirstProbeSum="+461557.0ns" >
      </FlowStats>
      <FlowStats  flowId="35" packets="46" bytes="1848" delayFromFirstProbeSum="+461557.0ns" >
      </FlowStats>
      <FlowStats  flowId="36" packets="46" bytes="1848" delayFromFirstProbeSum="+461557.0ns" >
      </FlowStats>
      <FlowStats  flowId="37" packets="46" bytes="1848" delayFromFirstProbeSum="+461557.0ns" >
      </FlowStats>
      <FlowStats  flowId="38" packets="46" bytes="1848" delayFromFirstProbeSum="+461557.0ns" >
      </FlowStats>
      <FlowStats  flowId="39" packets="46" bytes="1848" delayFromFirstProbeSum="+461557.0ns" >
      </FlowStats>
      <FlowStats  flowId="40" packets="46" bytes="1848" delayFromFirstProbeSum="+461557.0ns" >
      </FlowStats>
      <FlowStats  flowId="41" packets="46" bytes="1848" delayFromFirstProbeSum="+461557.0ns" >
      </FlowStats>
      <FlowStats  flowId="42" packets="46" bytes="1848" delayFromFirstProbeSum="+461557.0ns" >
      </FlowStats>
      <FlowStats  flowId="43" packets="46" bytes="1848" delayFromFirstProbeSum="+461557.0ns" >
      </FlowStats>
      <FlowStats  flowId="44" packets="46" bytes="1848" delayFromFirstProbeSum="+461557.0ns" >
      </FlowStats>
      <FlowStats  flowId="45" packets="46" bytes="1848" delayFromFirstProbeSum="+461557.0ns" >
      </FlowStats>
      <FlowStats  flowId="46" packets="46" bytes="1848" delayFromFirstProbeSum="+461557.0ns" >
      </FlowStats>
      <FlowStats  flowId="47" packets="46" bytes="1848" delayFromFirstProbeSum="+461557.0ns" >
      </FlowStats>
      <FlowStats  flowId="48" packets="46" bytes="1848" delayFromFirstProbeSum="+461557.0ns" >
      </FlowStats>
      <FlowStats  flowId="49" packets="46" bytes="1848" delayFromFirstProbeSum="+461557.0ns" >
      </FlowStats>
      <FlowStats  flowId="50" packets="46" bytes="1848" delayFromFirstProbeSum="+461557.0ns" >
      </FlowStats>
      <FlowStats  flowId="51" packets="46" bytes="1848" delayFromFirstProbeSum="+461557.0ns" >
      </FlowStats>
      <FlowStats  flowId="52" packets="46" bytes="1848" delayFromFirstProbeSum="+461557.0ns" >
      </FlowStats>
      <FlowStats  flowId="53" packets="46" bytes="1848" delayFromFirstProbeSum="+461557.0ns" >
      </FlowStats>
      <FlowStats  flowId="54" packets="46" bytes="1848" delayFromFirstProbeSum="+461557.0ns" >
      </FlowStats>
      <FlowStats  flowId="55" packets="46" bytes="1848" delayFromFirstProbeSum="+461557.0ns" >
      </FlowStats>
      <FlowStats  flowId="56" packets="46" bytes="1848" delayFromFirstProbeSum="+461557.0ns" >
      </FlowStats>
    </FlowProbe>
    <FlowProbe index="3">
    </FlowProbe>
    <FlowProbe index="4">
      <FlowStats  flowId="1" packets="14064" bytes="21093088" delayFromFirstProbeSum="+0.0ns" >
      </FlowStats>
      <FlowStats  flowId="4" packets="13988" bytes="559528" delayFromFirstProbeSum="+421024830.0ns" >
      </FlowStats>
    </FlowProbe>
    <FlowProbe index="5">
    </FlowProbe>
    <FlowProbe index="6">
      <FlowStats  flowId="2" packets="13411" bytes="20113588" delayFromFirstProbeSum="+0.0ns" >
      </FlowStats>
      <FlowStats  flowId="5" packets="13340" bytes="533608" delayFromFirstProbeSum="+401520678.0ns" >
      </FlowStats>
    </FlowProbe>
    <FlowProbe index="7">
    </FlowProbe>
    <FlowProbe index="8">
      <FlowStats  flowId="3" packets="13053" bytes="19576588" delayFromFirstProbeSum="+0.0ns" >
      </FlowStats>
      <FlowStats  flowId="6" packets="12984" bytes="519368" delayFromFirstProbeSum="+390805434.0ns" >
      </FlowStats>
    </FlowProbe>
    <FlowProbe index="9">
    </FlowProbe>
    <FlowProbe index="10">
      <FlowStats  flowId="7" packets="47" bytes="65888" delayFromFirstProbeSum="+0.0ns" >
      </FlowStats>
      <FlowStats  flowId="32" packets="46" bytes="1848" delayFromFirstProbeSum="+1384605.0ns" >
      </FlowStats>
    </FlowProbe>
    <FlowProbe index="11">
    </FlowProbe>
    <FlowProbe index="12">
      <FlowStats  flowId="8" packets="47" bytes="65888" delayFromFirstProbeSum="+0.0ns" >
      </FlowStats>
      <FlowStats  flowId="33" packets="46" bytes="1848" delayFromFirstProbeSum="+1384605.0ns" >
      </FlowStats>
    </FlowProbe>
    <FlowProbe index="13">
    </FlowProbe>
    <FlowProbe index="14">
      <FlowStats  flowId="9" packets="47" bytes="65888" delayFromFirstProbeSum="+0.0ns" >
      </FlowStats>
      <FlowStats  flowId="34" packets="46" bytes="1848" delayFromFirstProbeSum="+1384605.0ns" >
      </FlowStats>
    </FlowProbe>
    <FlowProbe index="15">
    </FlowProbe>
    <FlowProbe index="16">
      <FlowStats  flowId="10" packets="47" bytes="65888" delayFromFirstProbeSum="+0.0ns" >
      </FlowStats>
      <FlowStats  flowId="35" packets="46" bytes="1848" delayFromFirstProbeSum="+1384605.0ns" >
      </FlowStats>
    </FlowProbe>
    <FlowProbe index="17">
    </FlowProbe>
    <FlowProbe index="18">
      <FlowStats  flowId="11" packets="47" bytes="65888" delayFromFirstProbeSum="+0.0ns" >
      </FlowStats>
      <FlowStats  flowId="36" packets="46" bytes="1848" delayFromFirstProbeSum="+1384605.0ns" >
      </FlowStats>
    </FlowProbe>
    <FlowProbe index="19">
    </FlowProbe>
    <FlowProbe index="20">
      <FlowStats  flowId="12" packets="47" bytes="65888" delayFromFirstProbeSum="+0.0ns" >
      </FlowStats>
      <FlowStats  flowId="37" packets="46" bytes="1848" delayFromFirstProbeSum="+1384605.0ns" >
      </FlowStats>
    </FlowProbe>
    <FlowProbe index="21">
    </FlowProbe>
    <FlowProbe index="22">
      <FlowStats  flowId="13" packets="47" bytes="65888" delayFromFirstProbeSum="+0.0ns" >
      </FlowStats>
      <FlowStats  flowId="38" packets="46" bytes="1848" delayFromFirstProbeSum="+1384605.0ns" >
      </FlowStats>
    </FlowProbe>
    <FlowProbe index="23">
    </FlowProbe>
    <FlowProbe index="24">
      <FlowStats  flowId="14" packets="47" bytes="65888" delayFromFirstProbeSum="+0.0ns" >
      </FlowStats>
      <FlowStats  flowId="39" packets="46" bytes="1848" delayFromFirstProbeSum="+1384605.0ns" >
      </FlowStats>
    </FlowProbe>
    <FlowProbe index="25">
    </FlowProbe>
    <FlowProbe index="26">
      <FlowStats  flowId="15" packets="47" bytes="65888" delayFromFirstProbeSum="+0.0ns" >
      </FlowStats>
      <FlowStats  flowId="40" packets="46" bytes="1848" delayFromFirstProbeSum="+1384605.0ns" >
      </FlowStats>
    </FlowProbe>
    <FlowProbe index="27">
    </FlowProbe>
    <FlowProbe index="28">
      <FlowStats  flowId="16" packets="47" bytes="65888" delayFromFirstProbeSum="+0.0ns" >
      </FlowStats>
      <FlowStats  flowId="41" packets="46" bytes="1848" delayFromFirstProbeSum="+1384605.0ns" >
      </FlowStats>
    </FlowProbe>
    <FlowProbe index="29">
    </FlowProbe>
    <FlowProbe index="30">
      <FlowStats  flowId="17" packets="47" bytes="65888" delayFromFirstProbeSum="+0.0ns" >
      </FlowStats>
      <FlowStats  flowId="42" packets="46" bytes="1848" delayFromFirstProbeSum="+1384605.0ns" >
      </FlowStats>
    </FlowProbe>
    <FlowProbe index="31">
    </FlowProbe>
    <FlowProbe index="32">
      <FlowStats  flowId="18" packets="47" bytes="65888" delayFromFirstProbeSum="+0.0ns" >
      </FlowStats>
      <FlowStats  flowId="43" packets="46" bytes="1848" delayFromFirstProbeSum="+1384605.0ns" >
      </FlowStats>
    </FlowProbe>
    <FlowProbe index="33">
    </FlowProbe>
    <FlowProbe index="34">
      <FlowStats  flowId="19" packets="47" bytes="65888" delayFromFirstProbeSum="+0.0ns" >
      </FlowStats>
      <FlowStats  flowId="44" packets="46" bytes="1848" delayFromFirstProbeSum="+1384605.0ns" >
      </FlowStats>
    </FlowProbe>
    <FlowProbe index="35">
    </FlowProbe>
    <FlowProbe index="36">
      <FlowStats  flowId="20" packets="47" bytes="65888" delayFromFirstProbeSum="+0.0ns" >
      </FlowStats>
      <FlowStats  flowId="45" packets="46" bytes="1848" delayFromFirstProbeSum="+1384605.0ns" >
      </FlowStats>
    </FlowProbe>
    <FlowProbe index="37">
    </FlowProbe>
    <FlowProbe index="38">
      <FlowStats  flowId="21" packets="47" bytes="65888" delayFromFirstProbeSum="+0.0ns" >
      </FlowStats>
      <FlowStats  flowId="46" packets="46" bytes="1848" delayFromFirstProbeSum="+1384605.0ns" >
      </FlowStats>
    </FlowProbe>
    <FlowProbe index="39">
    </FlowProbe>
    <FlowProbe index="40">
      <FlowStats  flowId="22" packets="47" bytes="65888" delayFromFirstProbeSum="+0.0ns" >
      </FlowStats>
      <FlowStats  flowId="47" packets="46" bytes="1848" delayFromFirstProbeSum="+1384605.0ns" >
      </FlowStats>
    </FlowProbe>
    <FlowProbe index="41">
    </FlowProbe>
    <FlowProbe index="42">
      <FlowStats  flowId="23" packets="47" bytes="65888" delayFromFirstProbeSum="+0.0ns" >
      </FlowStats>
      <FlowStats  flowId="48" packets="46" bytes="1848" delayFromFirstProbeSum="+1384605.0ns" >
      </FlowStats>
    </FlowProbe>
    <FlowProbe index="43">
    </FlowProbe>
    <FlowProbe index="44">
      <FlowStats  flowId="24" packets="47" bytes="65888" delayFromFirstProbeSum="+0.0ns" >
      </FlowStats>
      <FlowStats  flowId="49" packets="46" bytes="1848" delayFromFirstProbeSum="+1384605.0ns" >
      </FlowStats>
    </FlowProbe>
    <FlowProbe index="45">
    </FlowProbe>
    <FlowProbe index="46">
      <FlowStats  flowId="25" packets="47" bytes="65888" delayFromFirstProbeSum="+0.0ns" >
      </FlowStats>
      <FlowStats  flowId="50" packets="46" bytes="1848" delayFromFirstProbeSum="+1384605.0ns" >
      </FlowStats>
    </FlowProbe>
    <FlowProbe index="47">
    </FlowProbe>
    <FlowProbe index="48">
      <FlowStats  flowId="26" packets="47" bytes="65888" delayFromFirstProbeSum="+0.0ns" >
      </FlowStats>
      <FlowStats  flowId="51" packets="46" bytes="1848" delayFromFirstProbeSum="+1384605.0ns" >
      </FlowStats>
    </FlowProbe>
    <FlowProbe index="49">
    </FlowProbe>
    <FlowProbe index="50">
      <FlowStats  flowId="27" packets="47" bytes="65888" delayFromFirstProbeSum="+0.0ns" >
      </FlowStats>
      <FlowStats  flowId="52" packets="46" bytes="1848" delayFromFirstProbeSum="+1384605.0ns" >
      </FlowStats>
    </FlowProbe>
    <FlowProbe index="51">
    </FlowProbe>
    <FlowProbe index="52">
      <FlowStats  flowId="28" packets="47" bytes="65888" delayFromFirstProbeSum="+0.0ns" >
      </FlowStats>
      <FlowStats  flowId="53" packets="46" bytes="1848" delayFromFirstProbeSum="+1384605.0ns" >
      </FlowStats>
    </FlowProbe>
    <FlowProbe index="53">
    </FlowProbe>
    <FlowProbe index="54">
      <FlowStats  flowId="29" packets="47" bytes="65888" delayFromFirstProbeSum="+0.0ns" >
      </FlowStats>
      <FlowStats  flowId="54" packets="46" bytes="1848" delayFromFirstProbeSum="+1384605.0ns" >
      </FlowStats>
    </FlowProbe>
    <FlowProbe index="55">
    </FlowProbe>
    <FlowProbe index="56">
      <FlowStats  flowId="30" packets="47" bytes="65888" delayFromFirstProbeSum="+0.0ns" >
      </FlowStats>
      <FlowStats  flowId="55" packets="46" bytes="1848" delayFromFirstProbeSum="+1384605.0ns" >
      </FlowStats>
    </FlowProbe>
    <FlowProbe index="57">
    </FlowProbe>
    <FlowProbe index="58">
      <FlowStats  flowId="31" packets="47" bytes="65888" delayFromFirstProbeSum="+0.0ns" >
      </FlowStats>
      <FlowStats  flowId="56" packets="46" bytes="1848" delayFromFirstProbeSum="+1384605.0ns" >
      </FlowStats>
    </FlowProbe>
    <FlowProbe index="59">
    </FlowProbe>
    <FlowProbe index="60">
      <FlowStats  flowId="1" packets="13989" bytes="20980588" delayFromFirstProbeSum="+2989008582.0ns" >
      </FlowStats>
      <FlowStats  flowId="2" packets="13362" bytes="20040088" delayFromFirstProbeSum="+2875176146.0ns" >
      </FlowStats>
      <FlowStats  flowId="3" packets="12989" bytes="19480588" delayFromFirstProbeSum="+2768548742.0ns" >
      </FlowStats>
      <FlowStats  flowId="4" packets="13988" bytes="559528" delayFromFirstProbeSum="+0.0ns" >
      </FlowStats>
      <FlowStats  flowId="5" packets="13361" bytes="534448" delayFromFirstProbeSum="+0.0ns" >
      </FlowStats>
      <FlowStats  flowId="6" packets="12988" bytes="519528" delayFromFirstProbeSum="+0.0ns" >
      </FlowStats>
    </FlowProbe>
    <FlowProbe index="61">
    </FlowProbe>
    <FlowProbe index="62">
      <FlowStats  flowId="7" packets="47" bytes="65888" delayFromFirstProbeSum="+11819499.0ns" >
      </FlowStats>
      <FlowStats  flowId="8" packets="47" bytes="65888" delayFromFirstProbeSum="+11827318.0ns" >
      </FlowStats>
      <FlowStats  flowId="9" packets="47" bytes="65888" delayFromFirstProbeSum="+11836146.0ns" >
      </FlowStats>
      <FlowStats  flowId="10" packets="47" bytes="65888" delayFromFirstProbeSum="+11844974.0ns" >
      </FlowStats>
      <FlowStats  flowId="11" packets="47" bytes="65888" delayFromFirstProbeSum="+11983678.0ns" >
      </FlowStats>
      <FlowStats  flowId="12" packets="47" bytes="65888" delayFromFirstProbeSum="+11998703.0ns" >
      </FlowStats>
      <FlowStats  flowId="13" packets="47" bytes="65888" delayFromFirstProbeSum="+12014737.0ns" >
      </FlowStats>
      <FlowStats  flowId="14" packets="47" bytes="65888" delayFromFirstProbeSum="+12028369.0ns" >
      </FlowStats>
      <FlowStats  flowId="15" packets="47" bytes="65888" delayFromFirstProbeSum="+12042001.0ns" >
      </FlowStats>
      <FlowStats  flowId="16" packets="47" bytes="65888" delayFromFirstProbeSum="+12055633.0ns" >
      </FlowStats>
      <FlowStats  flowId="17" packets="47" bytes="65888" delayFromFirstProbeSum="+12068064.0ns" >
      </FlowStats>
      <FlowStats  flowId="18" packets="47" bytes="65888" delayFromFirstProbeSum="+12080495.0ns" >
      </FlowStats>
      <FlowStats  flowId="19" packets="47" bytes="65888" delayFromFirstProbeSum="+12092926.0ns" >
      </FlowStats>
      <FlowStats  flowId="20" packets="47" bytes="65888" delayFromFirstProbeSum="+12105357.0ns" >
      </FlowStats>
      <FlowStats  flowId="21" packets="47" bytes="65888" delayFromFirstProbeSum="+12117788.0ns" >
      </FlowStats>
      <FlowStats  flowId="22" packets="47" bytes="65888" delayFromFirstProbeSum="+12130219.0ns" >
      </FlowStats>
      <FlowStats  flowId="23" packets="47" bytes="65888" delayFromFirstProbeSum="+12142650.0ns" >
      </FlowStats>
      <FlowStats  flowId="24" packets="47" bytes="65888" delayFromFirstProbeSum="+12155081.0ns" >
      </FlowStats>
      <FlowStats  flowId="25" packets="47" bytes="65888" delayFromFirstProbeSum="+12167512.0ns" >
      </FlowStats>
      <FlowStats  flowId="26" packets="47" bytes="65888" delayFromFirstProbeSum="+12179943.0ns" >
      </FlowStats>
      <FlowStats  flowId="27" packets="47" bytes="65888" delayFromFirstProbeSum="+12192374.0ns" >
      </FlowStats>
      <FlowStats  flowId="28" packets="47" bytes="65888" delayFromFirstProbeSum="+12204805.0ns" >
      </FlowStats>
      <FlowStats  flowId="29" packets="47" bytes="65888" delayFromFirstProbeSum="+12217236.0ns" >
      </FlowStats>
      <FlowStats  flowId="30" packets="47" bytes="65888" delayFromFirstProbeSum="+12229667.0ns" >
      </FlowStats>
      <FlowStats  flowId="31" packets="47" bytes="65888" delayFromFirstProbeSum="+12244500.0ns" >
      </FlowStats>
      <FlowStats  flowId="32" packets="46" bytes="1848" delayFromFirstProbeSum="+0.0ns" >
      </FlowStats>
      <FlowStats  flowId="33" packets="46" bytes="1848" delayFromFirstProbeSum="+0.0ns" >
      </FlowStats>
      <FlowStats  flowId="34" packets="46" bytes="1848" delayFromFirstProbeSum="+0.0ns" >
      </FlowStats>
      <FlowStats  flowId="35" packets="46" bytes="1848" delayFromFirstProbeSum="+0.0ns" >
      </FlowStats>
      <FlowStats  flowId="36" packets="46" bytes="1848" delayFromFirstProbeSum="+0.0ns" >
      </FlowStats>
      <FlowStats  flowId="37" packets="46" bytes="1848" delayFromFirstProbeSum="+0.0ns" >
      </FlowStats>
      <FlowStats  flowId="38" packets="46" bytes="1848" delayFromFirstProbeSum="+0.0ns" >
      </FlowStats>
      <FlowStats  flowId="39" packets="46" bytes="1848" delayFromFirstProbeSum="+0.0ns" >
      </FlowStats>
      <FlowStats  flowId="40" packets="46" bytes="1848" delayFromFirstProbeSum="+0.0ns" >
      </FlowStats>
      <FlowStats  flowId="41" packets="46" bytes="1848" delayFromFirstProbeSum="+0.0ns" >
      </FlowStats>
      <FlowStats  flowId="42" packets="46" bytes="1848" delayFromFirstProbeSum="+0.0ns" >
      </FlowStats>
      <FlowStats  flowId="43" packets="46" bytes="1848" delayFromFirstProbeSum="+0.0ns" >
      </FlowStats>
      <FlowStats  flowId="44" packets="46" bytes="1848" delayFromFirstProbeSum="+0.0ns" >
      </FlowStats>
      <FlowStats  flowId="45" packets="46" bytes="1848" delayFromFirstProbeSum="+0.0ns" >
      </FlowStats>
      <FlowStats  flowId="46" packets="46" bytes="1848" delayFromFirstProbeSum="+0.0ns" >
      </FlowStats>
      <FlowStats  flowId="47" packets="46" bytes="1848" delayFromFirstProbeSum="+0.0ns" >
      </FlowStats>
      <FlowStats  flowId="48" packets="46" bytes="1848" delayFromFirstProbeSum="+0.0ns" >
      </FlowStats>
      <FlowStats  flowId="49" packets="46" bytes="1848" delayFromFirstProbeSum="+0.0ns" >
      </FlowStats>
      <FlowStats  flowId="50" packets="46" bytes="1848" delayFromFirstProbeSum="+0.0ns" >
      </FlowStats>
      <FlowStats  flowId="51" packets="46" bytes="1848" delayFromFirstProbeSum="+0.0ns" >
      </FlowStats>
      <FlowStats  flowId="52" packets="46" bytes="1848" delayFromFirstProbeSum="+0.0ns" >
      </FlowStats>
      <FlowStats  flowId="53" packets="46" bytes="1848" delayFromFirstProbeSum="+0.0ns" >
      </FlowStats>
      <FlowStats  flowId="54" packets="46" bytes="1848" delayFromFirstProbeSum="+0.0ns" >
      </FlowStats>
      <FlowStats  flowId="55" packets="46" bytes="1848" delayFromFirstProbeSum="+0.0ns" >
      </FlowStats>
      <FlowStats  flowId="56" packets="46" bytes="1848" delayFromFirstProbeSum="+0.0ns" >
      </FlowStats>
    </FlowProbe>
    <FlowProbe index="63">
    </FlowProbe>
  </FlowProbes>
</FlowMonitor>
